{"verses":{"1":[{"w":"שִׁ֗יר","translit":"šîr","strongs":"H7892","morph":"N-msc","gloss":"A song"},{"w":"הַֽמַּ֫עֲל֥וֹת","translit":"ham·ma·‘ă·lō·wṯ","strongs":"H4609","morph":"Art | N-fp","gloss":"of ascents"},{"w":"רַ֭בַּת","translit":"rab·baṯ","strongs":"H7227","morph":"Adj-fsc","gloss":"Many a time"},{"w":"צְרָר֣וּנִי","translit":"ṣə·rā·rū·nî","strongs":"H6887","morph":"V-Qal-Perf-3cp | 1cs","gloss":"they have persecuted me"},{"w":"מִנְּעוּרַ֑י","translit":"min·nə·‘ū·ray","strongs":"H5271","morph":"Prep-m | N-mpc | 1cs","gloss":"from my youth"},{"w":"יִשְׂרָאֵֽל׃","translit":"yiś·rā·’êl","strongs":"H3478","morph":"N-proper-ms","gloss":"let Israel"},{"w":"נָ֝א","translit":"nā","strongs":"H4994","morph":"Interjection","gloss":"now"},{"w":"יֹֽאמַר־","translit":"yō·mar-","strongs":"H559","morph":"V-Qal-Imperf-3ms","gloss":"declare"}],"2":[{"w":"רַ֭בַּת","translit":"rab·baṯ","strongs":"H7227","morph":"Adj-fsc","gloss":"many a time"},{"w":"צְרָר֣וּנִי","translit":"ṣə·rā·rū·nî","strongs":"H6887","morph":"V-Qal-Perf-3cp | 1cs","gloss":"they have persecuted me"},{"w":"מִנְּעוּרָ֑י","translit":"min·nə·‘ū·rāy","strongs":"H5271","morph":"Prep-m | N-mpc | 1cs","gloss":"from my youth"},{"w":"גַּ֝ם","translit":"gam","strongs":"H1571","morph":"Conj","gloss":"but"},{"w":"לֹא־","translit":"lō-","strongs":"H3808","morph":"Adv-NegPrt","gloss":"they have not"},{"w":"יָ֥כְלוּ","translit":"yā·ḵə·lū","strongs":"H3201","morph":"V-Qal-Perf-3cp","gloss":"prevailed"},{"w":"לִֽי׃","translit":"lî","morph":"Prep | 1cs","gloss":"against me"}],"3":[{"w":"חָרְשׁ֣וּ","translit":"ḥā·rə·šū","strongs":"H2790","morph":"V-Qal-Perf-3cp","gloss":"The plowmen"},{"w":"חֹרְשִׁ֑ים","translit":"ḥō·rə·šîm","strongs":"H2790","morph":"V-Qal-Prtcpl-mp","gloss":"plowed"},{"w":"עַל־","translit":"‘al-","strongs":"H5921","morph":"Prep","gloss":"over"},{"w":"גַּ֭בִּי","translit":"gab·bî","strongs":"H1354","morph":"N-csc | 1cs","gloss":"my back"},{"w":"לְמַעֲנוֹתָם׃","translit":"lə·ma·ʿă·nō·ṯå̄m","strongs":"H4618","morph":"Prep-l | N-fpc | 3mp","gloss":"they made their furrows"},{"w":"הֶ֝אֱרִ֗יכוּ","translit":"he·’ĕ·rî·ḵū","strongs":"H748","morph":"V-Hifil-Perf-3cp","gloss":"long"}],"4":[{"w":"יְהוָ֥ה","translit":"Yah·weh","strongs":"H3068","morph":"N-proper-ms","gloss":"The LORD"},{"w":"צַדִּ֑יק","translit":"ṣad·dîq","strongs":"H6662","morph":"Adj-ms","gloss":"is righteous"},{"w":"קִ֝צֵּ֗ץ","translit":"qiṣ·ṣêṣ","strongs":"H7112","morph":"V-Piel-Perf-3ms","gloss":"He has cut me"},{"w":"עֲב֣וֹת","translit":"‘ă·ḇō·wṯ","strongs":"H5688","morph":"N-csc","gloss":"from the cords"},{"w":"רְשָׁעִֽים׃","translit":"rə·šā·‘îm","strongs":"H7563","morph":"Adj-mp","gloss":"of the wicked"}],"5":[{"w":"כֹּ֝֗ל","translit":"kōl","strongs":"H3605","morph":"N-msc","gloss":"May all"},{"w":"שֹׂנְאֵ֥י","translit":"śō·nə·’ê","strongs":"H8130","morph":"V-Qal-Prtcpl-mpc","gloss":"who hate"},{"w":"צִיּֽוֹן׃","translit":"ṣî·yō·wn","strongs":"H6726","morph":"N-proper-fs","gloss":"Zion"},{"w":"וְיִסֹּ֣גוּ","translit":"wə·yis·sō·ḡū","strongs":"H5472","morph":"Conj-w | V-Nifal-ConjImperf-3mp","gloss":"be turned"},{"w":"אָח֑וֹר","translit":"’ā·ḥō·wr","strongs":"H268","morph":"N-ms","gloss":"back"},{"w":"יֵ֭בֹשׁוּ","translit":"yê·ḇō·šū","strongs":"H954","morph":"V-Qal-Imperf-3mp","gloss":"in shame"}],"6":[{"w":"יִ֭הְיוּ","translit":"yih·yū","strongs":"H1961","morph":"V-Qal-Imperf-3mp","gloss":"May they be"},{"w":"כַּחֲצִ֣יר","translit":"ka·ḥă·ṣîr","strongs":"H2682","morph":"Prep-k | N-msc","gloss":"like grass"},{"w":"גַּגּ֑וֹת","translit":"gag·gō·wṯ","strongs":"H1406","morph":"N-mp","gloss":"on the rooftops"},{"w":"יָבֵֽשׁ׃","translit":"yā·ḇêš","strongs":"H3001","morph":"V-Qal-Perf-3ms","gloss":"which withers"},{"w":"שֶׁקַּדְמַ֖ת","translit":"šeq·qaḏ·maṯ","strongs":"H6927","morph":"Pro-r | N-fsc","gloss":"before"},{"w":"שָׁלַ֣ף","translit":"šā·lap̄","strongs":"H8025","morph":"V-Qal-Perf-3ms","gloss":"it can grow"}],"7":[{"w":"שֶׁלֹּ֤א","translit":"šel·lō","strongs":"H3808","morph":"Pro-r | Adv-NegPrt","gloss":"unable"},{"w":"מִלֵּ֖א","translit":"mil·lê","strongs":"H4390","morph":"V-Piel-Perf-3ms","gloss":"to fill"},{"w":"כַפּ֥וֹ","translit":"ḵap·pōw","strongs":"H3709","morph":"N-fsc | 3ms","gloss":"the hands"},{"w":"קוֹצֵ֗ר","translit":"qō·w·ṣêr","strongs":"H7114","morph":"V-Qal-Prtcpl-ms","gloss":"of the reaper"},{"w":"וְחִצְנ֥וֹ","translit":"wə·ḥiṣ·nōw","strongs":"H2683","morph":"Conj-w | N-msc | 3ms","gloss":"or the arms"},{"w":"מְעַמֵּֽר׃","translit":"mə·‘am·mêr","strongs":"H6014","morph":"V-Piel-Prtcpl-ms","gloss":"of the binder of sheaves"}],"8":[{"w":"וְלֹ֤א","translit":"wə·lō","strongs":"H3808","morph":"Conj-w | Adv-NegPrt","gloss":"May none"},{"w":"הָעֹבְרִ֗ים","translit":"hā·‘ō·ḇə·rîm","strongs":"H5674","morph":"Art | V-Qal-Prtcpl-mp","gloss":"who pass by"},{"w":"אָֽמְר֨וּ׀","translit":"’ā·mə·rū","strongs":"H559","morph":"V-Qal-Perf-3cp","gloss":"say [to them]"},{"w":"בִּרְכַּֽת־","translit":"bir·kaṯ-","strongs":"H1293","morph":"N-fsc","gloss":"The blessing"},{"w":"יְהוָ֥ה","translit":"Yah·weh","strongs":"H3068","morph":"N-proper-ms","gloss":"of the LORD"},{"w":"אֲלֵיכֶ֑ם","translit":"’ă·lê·ḵem","strongs":"H413","morph":"Prep | 2mp","gloss":"be on you"},{"w":"בֵּרַ֥כְנוּ","translit":"bê·raḵ·nū","strongs":"H1288","morph":"V-Piel-Perf-1cp","gloss":"we bless"},{"w":"אֶ֝תְכֶ֗ם","translit":"’eṯ·ḵem","strongs":"H853","morph":"DirObjM | 2mp","gloss":"you"},{"w":"בְּשֵׁ֣ם","translit":"bə·šêm","strongs":"H8034","morph":"Prep-b | N-msc","gloss":"in the name"},{"w":"יְהוָֽה׃","translit":"Yah·weh","strongs":"H3068","morph":"N-proper-ms","gloss":"of the LORD"}]}}