{"verses":{"1":[{"w":"יִשְׂרָאֵ֔ל","translit":"yiś·rā·’êl","strongs":"H3478","morph":"N-proper-ms","gloss":"Israel"},{"w":"בּוֹקֵק֙","translit":"bō·w·qêq","strongs":"H1238","morph":"V-Qal-Prtcpl-ms","gloss":"was a luxuriant"},{"w":"גֶּ֤פֶן","translit":"ge·p̄en","strongs":"H1612","morph":"N-cs","gloss":"vine"},{"w":"יְשַׁוֶּה־","translit":"yə·šaw·weh-","strongs":"H7737","morph":"V-Piel-Imperf-3ms","gloss":"yielding"},{"w":"פְּרִ֖י","translit":"pə·rî","strongs":"H6529","morph":"N-ms","gloss":"fruit"},{"w":"לּ֑וֹ","translit":"lōw","morph":"Prep | 3ms","gloss":"for himself"},{"w":"לְפִרְי֗וֹ","translit":"lə·p̄ir·yōw","strongs":"H6529","morph":"Prep-l | N-msc | 3ms","gloss":"The more his fruit"},{"w":"כְּרֹ֣ב","translit":"kə·rōḇ","strongs":"H7230","morph":"Prep-k | N-ms","gloss":"increased"},{"w":"הִרְבָּה֙","translit":"hir·bāh","strongs":"H7235","morph":"V-Hifil-Perf-3ms","gloss":"the more he increased"},{"w":"לַֽמִּזְבְּח֔וֹת","translit":"lam·miz·bə·ḥō·wṯ","strongs":"H4196","morph":"Prep-l, Art | N-mp","gloss":"the altars"},{"w":"כְּט֣וֹב","translit":"kə·ṭō·wḇ","strongs":"H2896","morph":"Prep-k | N-ms","gloss":"The better"},{"w":"לְאַרְצ֔וֹ","translit":"lə·’ar·ṣōw","strongs":"H776","morph":"Prep-l | N-fsc | 3ms","gloss":"his land produced"},{"w":"הֵיטִ֖יבוּ","translit":"hê·ṭî·ḇū","strongs":"H3190","morph":"V-Hifil-Perf-3cp","gloss":"the better he made"},{"w":"מַצֵּבֽוֹת׃","translit":"maṣ·ṣê·ḇō·wṯ","strongs":"H4676","morph":"N-fp","gloss":"the sacred pillars"}],"2":[{"w":"לִבָּ֖ם","translit":"lib·bām","strongs":"H3820","morph":"N-msc | 3mp","gloss":"Their hearts"},{"w":"חָלַ֥ק","translit":"ḥā·laq","strongs":"H2505","morph":"V-Qal-Perf-3ms","gloss":"are devious"},{"w":"עַתָּ֣ה","translit":"‘at·tāh","strongs":"H6258","morph":"Adv","gloss":"now"},{"w":"יֶאְשָׁ֑מוּ","translit":"ye’·šā·mū","strongs":"H816","morph":"V-Qal-Imperf-3mp","gloss":"they must bear their guilt"},{"w":"ה֚וּא","translit":"hū","strongs":"H1931","morph":"Pro-3ms","gloss":"The LORD"},{"w":"יַעֲרֹ֣ף","translit":"ya·‘ă·rōp̄","strongs":"H6202","morph":"V-Qal-Imperf-3ms","gloss":"will break down"},{"w":"מִזְבְּחוֹתָ֔ם","translit":"miz·bə·ḥō·w·ṯām","strongs":"H4196","morph":"N-mpc | 3mp","gloss":"their altars"},{"w":"יְשֹׁדֵ֖ד","translit":"yə·šō·ḏêḏ","strongs":"H7703","morph":"V-Piel-Imperf-3ms","gloss":"and demolish"},{"w":"מַצֵּבוֹתָֽם׃","translit":"maṣ·ṣê·ḇō·w·ṯām","strongs":"H4676","morph":"N-fpc | 3mp","gloss":"their sacred pillars"}],"3":[{"w":"כִּ֤י","translit":"kî","strongs":"H3588","morph":"Conj","gloss":"Surely"},{"w":"עַתָּה֙","translit":"‘at·tāh","strongs":"H6258","morph":"Adv","gloss":"now"},{"w":"יֹֽאמְר֔וּ","translit":"yō·mə·rū","strongs":"H559","morph":"V-Qal-Imperf-3mp","gloss":"they will say"},{"w":"לָ֑נוּ","translit":"lā·nū","morph":"Prep | 1cp","gloss":"We have"},{"w":"אֵ֥ין","translit":"’ên","strongs":"H369","morph":"Adv","gloss":"no"},{"w":"מֶ֖לֶךְ","translit":"me·leḵ","strongs":"H4428","morph":"N-ms","gloss":"king"},{"w":"כִּ֣י","translit":"kî","strongs":"H3588","morph":"Conj","gloss":"for"},{"w":"לֹ֤א","translit":"lō","strongs":"H3808","morph":"Adv-NegPrt","gloss":"we do not"},{"w":"יָרֵ֙אנוּ֙","translit":"yā·rê·nū","strongs":"H3372","morph":"V-Qal-Perf-1cp","gloss":"revere"},{"w":"אֶת־","translit":"’eṯ-","strongs":"H853","morph":"DirObjM","gloss":"-"},{"w":"יְהֹוָ֔ה","translit":"ha·šēm","strongs":"H3068","morph":"N-proper-ms","gloss":"the LORD"},{"w":"מַה־","translit":"mah-","strongs":"H4100","morph":"Interrog","gloss":"What"},{"w":"וְהַמֶּ֖לֶךְ","translit":"wə·ham·me·leḵ","strongs":"H4428","morph":"Conj-w, Art | N-ms","gloss":"can a king"},{"w":"יַּֽעֲשֶׂה־","translit":"ya·‘ă·śeh-","strongs":"H6213","morph":"V-Qal-Imperf-3ms","gloss":"do"},{"w":"לָּֽנוּ׃","translit":"lā·nū","morph":"Prep | 1cp","gloss":"for us"}],"4":[{"w":"דִּבְּר֣וּ","translit":"dib·bə·rū","strongs":"H1696","morph":"V-Piel-Perf-3cp","gloss":"They speak"},{"w":"דְבָרִ֔ים","translit":"ḏə·ḇā·rîm","strongs":"H1697","morph":"N-mp","gloss":"mere words"},{"w":"שָׁ֖וְא","translit":"šāw","strongs":"H7723","morph":"N-ms","gloss":"with false"},{"w":"אָל֥וֹת","translit":"’ā·lō·wṯ","strongs":"H422","morph":"V-Qal-InfAbs","gloss":"oaths"},{"w":"כָּרֹ֣ת","translit":"kā·rōṯ","strongs":"H3772","morph":"V-Qal-InfAbs","gloss":"they make"},{"w":"בְּרִ֑ית","translit":"bə·rîṯ","strongs":"H1285","morph":"N-fs","gloss":"covenants"},{"w":"מִשְׁפָּ֔ט","translit":"miš·pāṭ","strongs":"H4941","morph":"N-ms","gloss":"So judgment"},{"w":"וּפָרַ֤ח","translit":"ū·p̄ā·raḥ","strongs":"H6524","morph":"Conj-w | V-Qal-ConjPerf-3ms","gloss":"springs up"},{"w":"כָּרֹאשׁ֙","translit":"kā·rōš","strongs":"H7219","morph":"Prep-k, Art | N-ms","gloss":"like poisonous weeds"},{"w":"עַ֖ל","translit":"‘al","strongs":"H5921","morph":"Prep","gloss":"in"},{"w":"תַּלְמֵ֥י","translit":"tal·mê","strongs":"H8525","morph":"N-mpc","gloss":"the furrows"},{"w":"שָׂדָֽי׃","translit":"śā·ḏāy","strongs":"H7704","morph":"N-ms","gloss":"of a field"}],"5":[{"w":"שְׁכַ֣ן","translit":"šə·ḵan","strongs":"H7934","morph":"N-msc","gloss":"The people"},{"w":"שֹֽׁמְר֑וֹן","translit":"šō·mə·rō·wn","strongs":"H8111","morph":"N-proper-fs","gloss":"of Samaria"},{"w":"יָג֖וּרוּ","translit":"yā·ḡū·rū","strongs":"H1481","morph":"V-Qal-Imperf-3mp","gloss":"will fear"},{"w":"לְעֶגְלוֹת֙","translit":"lə·‘eḡ·lō·wṯ","strongs":"H5697","morph":"Prep-l | N-fpc","gloss":"for the calf"},{"w":"בֵּ֣ית","translit":"bêṯ","strongs":"H1007","morph":"Prep","gloss":"of"},{"w":"אָ֔וֶן","translit":"’ā·wen","strongs":"H1007","morph":"N-proper-fs","gloss":"Beth-aven"},{"w":"כִּי־","translit":"kî-","strongs":"H3588","morph":"Conj","gloss":"Indeed"},{"w":"עַמּ֗וֹ","translit":"‘am·mōw","strongs":"H5971","morph":"N-msc | 3ms","gloss":"its people"},{"w":"אָבַ֨ל","translit":"’ā·ḇal","strongs":"H56","morph":"V-Qal-Perf-3ms","gloss":"will mourn"},{"w":"עָלָ֜יו","translit":"‘ā·lāw","strongs":"H5921","morph":"Prep | 3ms","gloss":"over it"},{"w":"וּכְמָרָיו֙","translit":"ū·ḵə·mā·rāw","strongs":"H3649","morph":"Conj-w | N-mpc | 3ms","gloss":"with its idolatrous priests"},{"w":"עָלָ֣יו","translit":"‘ā·lāw","strongs":"H5921","morph":"Prep | 3ms"},{"w":"יָגִ֔ילוּ","translit":"yā·ḡî·lū","strongs":"H1523","morph":"V-Qal-Imperf-3mp","gloss":"those who rejoiced"},{"w":"עַל־","translit":"‘al-","strongs":"H5921","morph":"Prep","gloss":"in"},{"w":"כְּבוֹד֖וֹ","translit":"kə·ḇō·w·ḏōw","strongs":"H3519","morph":"N-msc | 3ms","gloss":"its glory"},{"w":"כִּֽי־","translit":"kî-","strongs":"H3588","morph":"Conj","gloss":"for"},{"w":"גָלָ֥ה","translit":"ḡā·lāh","strongs":"H1540","morph":"V-Qal-Perf-3ms","gloss":"it has been taken from them into exile"},{"w":"מִמֶּֽנּוּ׃","translit":"mim·men·nū","strongs":"H4480","morph":"Prep | 3ms"}],"6":[{"w":"גַּם־","translit":"gam-","strongs":"H1571","morph":"Conj","gloss":"Yes"},{"w":"אוֹתוֹ֙","translit":"’ō·w·ṯōw","strongs":"H853","morph":"DirObjM | 3ms","gloss":"-"},{"w":"יוּבָ֔ל","translit":"yū·ḇāl","strongs":"H2986","morph":"V-Hofal-Imperf-3ms","gloss":"it will be carried"},{"w":"לְאַשּׁ֣וּר","translit":"lə·’aš·šūr","strongs":"H804","morph":"Prep-l | N-proper-fs","gloss":"to Assyria"},{"w":"מִנְחָ֖ה","translit":"min·ḥāh","strongs":"H4503","morph":"N-fs","gloss":"as tribute"},{"w":"יָרֵ֑ב","translit":"yā·rêḇ","strongs":"H3377","morph":"N-proper-ms","gloss":"to the great"},{"w":"לְמֶ֣לֶךְ","translit":"lə·me·leḵ","strongs":"H4428","morph":"Prep-l | N-ms","gloss":"king"},{"w":"אֶפְרַ֣יִם","translit":"’ep̄·ra·yim","strongs":"H669","morph":"N-proper-ms","gloss":"Ephraim"},{"w":"יִקָּ֔ח","translit":"yiq·qāḥ","strongs":"H3947","morph":"V-Qal-Imperf-3ms","gloss":"will be seized"},{"w":"בָּשְׁנָה֙","translit":"bā·šə·nāh","strongs":"H1317","morph":"N-fs","gloss":"with shame"},{"w":"יִשְׂרָאֵ֖ל","translit":"yiś·rā·’êl","strongs":"H3478","morph":"N-proper-ms","gloss":"Israel"},{"w":"וְיֵב֥וֹשׁ","translit":"wə·yê·ḇō·wōš","strongs":"H954","morph":"Conj-w | V-Qal-ConjImperf-3ms","gloss":"will be ashamed"},{"w":"מֵעֲצָתֽוֹ׃","translit":"mê·‘ă·ṣā·ṯōw","strongs":"H6098","morph":"Prep-m | N-fsc | 3ms","gloss":"of its wooden idols"}],"7":[{"w":"שֹׁמְר֖וֹן","translit":"šō·mə·rō·wn","strongs":"H8111","morph":"N-proper-fs","gloss":"Samaria"},{"w":"נִדְמֶ֥ה","translit":"niḏ·meh","strongs":"H1820","morph":"V-Nifal-Prtcpl-ms","gloss":"will be carried off"},{"w":"מַלְכָּ֑הּ","translit":"mal·kāh","strongs":"H4428","morph":"N-msc | 3fs","gloss":"[with] her king"},{"w":"כְּקֶ֖צֶף","translit":"kə·qe·ṣep̄","strongs":"H7110","morph":"Prep-k | N-ms","gloss":"like a twig"},{"w":"עַל־","translit":"‘al-","strongs":"H5921","morph":"Prep","gloss":"on"},{"w":"פְּנֵי־","translit":"pə·nê-","strongs":"H6440","morph":"N-mpc","gloss":"the surface"},{"w":"מָֽיִם׃","translit":"mā·yim","strongs":"H4325","morph":"N-mp","gloss":"of the water"}],"8":[{"w":"בָּמ֣וֹת","translit":"bā·mō·wṯ","strongs":"H1116","morph":"N-fpc","gloss":"The high places"},{"w":"אָ֗וֶן","translit":"’ā·wen","strongs":"H205","morph":"N-ms","gloss":"of Aven"},{"w":"וְנִשְׁמְד֞וּ","translit":"wə·niš·mə·ḏū","strongs":"H8045","morph":"Conj-w | V-Nifal-ConjPerf-3cp","gloss":"will be destroyed"},{"w":"חַטַּאת֙","translit":"ḥaṭ·ṭaṯ","strongs":"H2403","morph":"N-fsc","gloss":"[it is] the sin"},{"w":"יִשְׂרָאֵ֔ל","translit":"yiś·rā·’êl","strongs":"H3478","morph":"N-proper-ms","gloss":"of Israel"},{"w":"ק֣וֹץ","translit":"qō·wṣ","strongs":"H6975","morph":"N-ms","gloss":"thorns"},{"w":"וְדַרְדַּ֔ר","translit":"wə·ḏar·dar","strongs":"H1863","morph":"Conj-w | N-ms","gloss":"and thistles"},{"w":"יַעֲלֶ֖ה","translit":"ya·‘ă·leh","strongs":"H5927","morph":"V-Qal-Imperf-3ms","gloss":"will overgrow"},{"w":"עַל־","translit":"‘al-","strongs":"H5921","morph":"Prep","gloss":". . ."},{"w":"מִזְבְּחוֹתָ֑ם","translit":"miz·bə·ḥō·w·ṯām","strongs":"H4196","morph":"N-mpc | 3mp","gloss":"their altars"},{"w":"וְאָמְר֤וּ","translit":"wə·’ā·mə·rū","strongs":"H559","morph":"Conj-w | V-Qal-ConjPerf-3cp","gloss":"Then they will say"},{"w":"לֶֽהָרִים֙","translit":"le·hā·rîm","strongs":"H2022","morph":"Prep-l, Art | N-mp","gloss":"to the mountains"},{"w":"כַּסּ֔וּנוּ","translit":"kas·sū·nū","strongs":"H3680","morph":"V-Piel-Imp-mp | 1cp","gloss":"Cover us"},{"w":"וְלַגְּבָע֖וֹת","translit":"wə·lag·gə·ḇā·‘ō·wṯ","strongs":"H1389","morph":"Conj-w, Prep-l, Art | N-fp","gloss":"and to the hills"},{"w":"נִפְל֥וּ","translit":"nip̄·lū","strongs":"H5307","morph":"V-Qal-Imp-mp","gloss":"Fall"},{"w":"עָלֵֽינוּ׃ס","translit":"‘ā·lê·nū","strongs":"H5921","morph":"Prep | 1cp","gloss":"on us"}],"9":[{"w":"מִימֵי֙","translit":"mî·mê","strongs":"H3117","morph":"Prep-m | N-mpc","gloss":"Since the days"},{"w":"הַגִּבְעָ֔ה","translit":"hag·giḇ·‘āh","strongs":"H1390","morph":"Art | N-proper-fs","gloss":"of Gibeah"},{"w":"חָטָ֖אתָ","translit":"ḥā·ṭā·ṯā","strongs":"H2398","morph":"V-Qal-Perf-2ms","gloss":"you have sinned"},{"w":"יִשְׂרָאֵ֑ל","translit":"yiś·rā·’êl","strongs":"H3478","morph":"N-proper-ms","gloss":"O Israel"},{"w":"שָׁ֣ם","translit":"šām","strongs":"H8033","morph":"Adv","gloss":"and there"},{"w":"עָמָ֔דוּ","translit":"‘ā·mā·ḏū","strongs":"H5975","morph":"V-Qal-Perf-3cp","gloss":"you have remained"},{"w":"לֹֽא־","translit":"lō-","strongs":"H3808","morph":"Adv-NegPrt","gloss":"Did not"},{"w":"מִלְחָמָ֖ה","translit":"mil·ḥā·māh","strongs":"H4421","morph":"N-fs","gloss":"the battle"},{"w":"בַּגִּבְעָ֛ה","translit":"bag·giḇ·‘āh","strongs":"H1390","morph":"Prep-b, Art | N-proper-fs","gloss":"in Gibeah"},{"w":"תַשִּׂיגֵ֧ם","translit":"ṯaś·śî·ḡêm","strongs":"H5381","morph":"V-Hifil-Imperf-3fs | 3mp","gloss":"overtake"},{"w":"עַל־","translit":"‘al-","strongs":"H5921","morph":"Prep"},{"w":"בְּנֵ֥י","translit":"bə·nê","strongs":"H1121","morph":"N-mpc","gloss":"the sons"},{"w":"עַֽלְוָֽה׃","translit":"‘al·wāh","strongs":"H5932","morph":"N-fs","gloss":"of iniquity"}],"10":[{"w":"וְאֶסֳּרֵ֑ם","translit":"wə·’es·so·rêm","strongs":"H3256","morph":"Conj-w | V-Qal-ConjImperf-1cs | 3mp","gloss":"I will chasten them"},{"w":"בְּאַוָּתִ֖י","translit":"bə·’aw·wā·ṯî","strongs":"H185","morph":"Prep-b | N-fsc | 1cs","gloss":"when I please"},{"w":"עַמִּ֔ים","translit":"‘am·mîm","strongs":"H5971","morph":"N-mp","gloss":"nations"},{"w":"וְאֻסְּפ֤וּ","translit":"wə·’us·sə·p̄ū","strongs":"H622","morph":"Conj-w | V-Piel-ConjPerf-3cp","gloss":"will be gathered"},{"w":"עֲלֵיהֶם֙","translit":"‘ă·lê·hem","strongs":"H5921","morph":"Prep | 3mp","gloss":"against them"},{"w":"בְּאָסְרָ֖ם","translit":"bə·’ā·sə·rām","strongs":"H631","morph":"Prep-b | V-Qal-Inf | 3mp","gloss":"to put them in bondage"},{"w":"לִשְׁתֵּ֥י","translit":"liš·tê","strongs":"H8147","morph":"Prep-l | Number-fdc","gloss":"for their double"},{"w":"עֵינֹתָם׃","translit":"ʿē·nō·ṯå̄m","strongs":"H5869","morph":"N-cpc | 3mp","gloss":"transgression"}],"11":[{"w":"וְאֶפְרַ֜יִם","translit":"wə·’ep̄·ra·yim","strongs":"H669","morph":"Conj-w | N-proper-ms","gloss":"Ephraim"},{"w":"מְלֻמָּדָה֙","translit":"mə·lum·mā·ḏāh","strongs":"H3925","morph":"V-Pual-Prtcpl-fs","gloss":"is a well-trained"},{"w":"עֶגְלָ֤ה","translit":"‘eḡ·lāh","strongs":"H5697","morph":"N-fs","gloss":"heifer"},{"w":"אֹהַ֣בְתִּי","translit":"’ō·haḇ·tî","strongs":"H157","morph":"V-Qal-Prtcpl-fsc","gloss":"that loves"},{"w":"לָד֔וּשׁ","translit":"lā·ḏūš","strongs":"H1758","morph":"Prep-l | V-Qal-Inf","gloss":"to thresh"},{"w":"וַאֲנִ֣י","translit":"wa·’ă·nî","strongs":"H589","morph":"Conj-w | Pro-1cs","gloss":"but I"},{"w":"עָבַ֔רְתִּי","translit":"‘ā·ḇar·tî","strongs":"H5674","morph":"V-Qal-Perf-1cs","gloss":"will place a yoke"},{"w":"עַל־","translit":"‘al-","strongs":"H5921","morph":"Prep","gloss":"on"},{"w":"ט֖וּב","translit":"ṭūḇ","strongs":"H2898","morph":"N-msc","gloss":"her fair"},{"w":"צַוָּארָ֑הּ","translit":"ṣaw·wā·rāh","strongs":"H6677","morph":"N-msc | 3fs","gloss":"neck"},{"w":"אַרְכִּ֤יב","translit":"’ar·kîḇ","strongs":"H7392","morph":"V-Hifil-Imperf-1cs","gloss":"I will harness"},{"w":"אֶפְרַ֙יִם֙","translit":"’ep̄·ra·yim","strongs":"H669","morph":"N-proper-ms","gloss":"Ephraim"},{"w":"יְהוּדָ֔ה","translit":"yə·hū·ḏāh","strongs":"H3063","morph":"N-proper-ms","gloss":"Judah"},{"w":"יַחֲר֣וֹשׁ","translit":"ya·ḥă·rō·wōš","strongs":"H2790","morph":"V-Qal-Imperf-3ms","gloss":"will plow"},{"w":"יַעֲקֹֽב׃","translit":"ya·‘ă·qōḇ","strongs":"H3290","morph":"N-proper-ms","gloss":"[and] Jacob"},{"w":"יְשַׂדֶּד־","translit":"yə·śad·deḏ-","strongs":"H7702","morph":"V-Piel-Imperf-3ms","gloss":"will break the hard ground"},{"w":"ל֖וֹ","translit":"lōw","morph":"Prep | 3ms"}],"12":[{"w":"זִרְע֨וּ","translit":"zir·‘ū","strongs":"H2232","morph":"V-Qal-Imp-mp","gloss":"Sow"},{"w":"לָכֶ֤ם","translit":"lā·ḵem","morph":"Prep | 2mp","gloss":"for yourselves"},{"w":"לִצְדָקָה֙","translit":"liṣ·ḏā·qāh","strongs":"H6666","morph":"Prep-l | N-fs","gloss":"righteousness"},{"w":"קִצְר֣וּ","translit":"qiṣ·rū","strongs":"H7114","morph":"V-Qal-Imp-mp","gloss":"and reap the fruit"},{"w":"לְפִי־","translit":"lə·p̄î-","strongs":"H6310","morph":"Prep-l | N-msc","gloss":". . ."},{"w":"חֶ֔סֶד","translit":"ḥe·seḏ","strongs":"H2617","morph":"N-ms","gloss":"of loving devotion"},{"w":"נִ֥ירוּ","translit":"nî·rū","strongs":"H5214","morph":"V-Qal-Imp-mp","gloss":"break up"},{"w":"לָכֶ֖ם","translit":"lā·ḵem","morph":"Prep | 2mp","gloss":"your"},{"w":"נִ֑יר","translit":"nîr","strongs":"H5215","morph":"N-ms","gloss":"unplowed ground"},{"w":"וְעֵת֙","translit":"wə·‘êṯ","strongs":"H6256","morph":"Conj-w | N-cs","gloss":"For [it is] time"},{"w":"לִדְר֣וֹשׁ","translit":"liḏ·rō·wōš","strongs":"H1875","morph":"Prep-l | V-Qal-Inf","gloss":"to seek"},{"w":"אֶת־","translit":"’eṯ-","strongs":"H853","morph":"DirObjM","gloss":"-"},{"w":"יְהוָ֔ה","translit":"Yah·weh","strongs":"H3068","morph":"N-proper-ms","gloss":"the LORD"},{"w":"עַד־","translit":"‘aḏ-","strongs":"H5704","morph":"Prep","gloss":"until"},{"w":"יָב֕וֹא","translit":"yā·ḇō·w","strongs":"H935","morph":"V-Qal-Imperf-3ms","gloss":"He comes"},{"w":"צֶ֖דֶק","translit":"ṣe·ḏeq","strongs":"H6664","morph":"N-ms","gloss":"and sends righteousness"},{"w":"לָכֶֽם׃","translit":"lā·ḵem","morph":"Prep | 2mp","gloss":"upon you"},{"w":"וְיֹרֶ֥ה","translit":"wə·yō·reh","strongs":"H3384","morph":"Conj-w | V-Hifil-ConjImperf-3ms","gloss":"like rain"}],"13":[{"w":"חֲרַשְׁתֶּם־","translit":"ḥă·raš·tem-","strongs":"H2790","morph":"V-Qal-Perf-2mp","gloss":"You have plowed"},{"w":"רֶ֛שַׁע","translit":"re·ša‘","strongs":"H7562","morph":"N-ms","gloss":"wickedness"},{"w":"קְצַרְתֶּ֖ם","translit":"qə·ṣar·tem","strongs":"H7114","morph":"V-Qal-Perf-2mp","gloss":"and reaped"},{"w":"עַוְלָ֥תָה","translit":"‘aw·lā·ṯāh","strongs":"H5766","morph":"N-fs","gloss":"injustice"},{"w":"אֲכַלְתֶּ֣ם","translit":"’ă·ḵal·tem","strongs":"H398","morph":"V-Qal-Perf-2mp","gloss":"you have eaten"},{"w":"פְּרִי־","translit":"pə·rî-","strongs":"H6529","morph":"N-msc","gloss":"the fruit"},{"w":"כָ֑חַשׁ","translit":"ḵā·ḥaš","strongs":"H3585","morph":"N-ms","gloss":"of lies"},{"w":"כִּֽי־","translit":"kî-","strongs":"H3588","morph":"Conj","gloss":"Because"},{"w":"בָטַ֥חְתָּ","translit":"ḇā·ṭaḥ·tā","strongs":"H982","morph":"V-Qal-Perf-2ms","gloss":"you have trusted"},{"w":"בְדַרְכְּךָ֖","translit":"ḇə·ḏar·kə·ḵā","strongs":"H1870","morph":"Prep-b | N-csc | 2ms","gloss":"in your own way"},{"w":"בְּרֹ֥ב","translit":"bə·rōḇ","strongs":"H7230","morph":"Prep-b | N-msc","gloss":"and in the multitude"},{"w":"גִּבּוֹרֶֽיךָ׃","translit":"gib·bō·w·re·ḵā","strongs":"H1368","morph":"Adj-mpc | 2ms","gloss":"of your mighty men"}],"14":[{"w":"שָׁאוֹן֮","translit":"šā·’ō·wn","strongs":"H7588","morph":"N-ms","gloss":"the roar of battle"},{"w":"וְקָ֣אם","translit":"wə·qām","strongs":"H6965","morph":"Conj-w | V-Qal-ConjPerf-3ms","gloss":"will rise"},{"w":"בְּעַמֶּךָ֒","translit":"bə·‘am·me·ḵā","strongs":"H5971","morph":"Prep-b | N-mpc | 2ms","gloss":"against your people"},{"w":"וְכָל־","translit":"wə·ḵāl","strongs":"H3605","morph":"Conj-w | N-msc","gloss":"so that all"},{"w":"מִבְצָרֶ֣יךָ","translit":"miḇ·ṣā·re·ḵā","strongs":"H4013","morph":"N-mpc | 2ms","gloss":"your fortresses"},{"w":"יוּשַּׁ֔ד","translit":"yūš·šaḏ","strongs":"H7703","morph":"V-QalPass-Imperf-3ms","gloss":"will be demolished"},{"w":"שַֽׁלְמַ֛ן","translit":"šal·man","strongs":"H8020","morph":"N-proper-ms","gloss":"as Shalman"},{"w":"בֵּ֥ית","translit":"bêṯ","strongs":"H1009","morph":"Prep"},{"w":"כְּשֹׁ֧ד","translit":"kə·šōḏ","strongs":"H7701","morph":"Prep-k | N-msc","gloss":"devastated"},{"w":"אַֽרְבֵ֖אל","translit":"’ar·ḇêl","strongs":"H1009","morph":"N-proper-fs","gloss":"Beth-arbel"},{"w":"בְּי֣וֹם","translit":"bə·yō·wm","strongs":"H3117","morph":"Prep-b | N-msc","gloss":"in the day"},{"w":"מִלְחָמָ֑ה","translit":"mil·ḥā·māh","strongs":"H4421","morph":"N-fs","gloss":"of battle"},{"w":"אֵ֥ם","translit":"’êm","strongs":"H517","morph":"N-fs","gloss":"when mothers"},{"w":"רֻטָּֽשָׁה׃","translit":"ruṭ·ṭā·šāh","strongs":"H7376","morph":"V-Pual-Perf-3fs","gloss":"were dashed to pieces"},{"w":"עַל־","translit":"‘al-","strongs":"H5921","morph":"Prep","gloss":"along with"},{"w":"בָּנִ֖ים","translit":"bā·nîm","strongs":"H1121","morph":"N-mp","gloss":"their children"}],"15":[{"w":"כָּ֗כָה","translit":"kā·ḵāh","strongs":"H3602","morph":"Adv","gloss":"Thus"},{"w":"עָשָׂ֤ה","translit":"‘ā·śāh","strongs":"H6213","morph":"V-Qal-Perf-3ms","gloss":"it will be done"},{"w":"לָכֶם֙","translit":"lā·ḵem","morph":"Prep | 2mp","gloss":"to you"},{"w":"בֵּֽית־","translit":"bêṯ-","strongs":"H1008","morph":"Prep","gloss":"vvv"},{"w":"אֵ֔ל","translit":"’êl","strongs":"H1008","morph":"N-proper-fs","gloss":"O Bethel"},{"w":"מִפְּנֵ֖י","translit":"mip·pə·nê","strongs":"H6440","morph":"Prep-m | N-cpc","gloss":"because of"},{"w":"רָֽעַתְכֶ֑ם","translit":"rā·‘aṯ·ḵem","strongs":"H7451","morph":"N-fsc | 2mp","gloss":"your great"},{"w":"רָעַ֣ת","translit":"rā·‘aṯ","strongs":"H7451","morph":"N-fsc","gloss":"wickedness"},{"w":"בַּשַּׁ֕חַר","translit":"baš·ša·ḥar","strongs":"H7837","morph":"Prep-b, Art | N-ms","gloss":"When the day dawns"},{"w":"מֶ֥לֶךְ","translit":"me·leḵ","strongs":"H4428","morph":"N-msc","gloss":"the king"},{"w":"יִשְׂרָאֵֽל׃","translit":"yiś·rā·’êl","strongs":"H3478","morph":"N-proper-ms","gloss":"of Israel"},{"w":"נִדְמֹ֥ה","translit":"niḏ·mōh","strongs":"H1820","morph":"V-Nifal-InfAbs","gloss":"will be utterly cut off"},{"w":"נִדְמָ֖ה","translit":"niḏ·māh","strongs":"H1820","morph":"V-Nifal-Perf-3ms","gloss":". . ."}]}}