{"verses":{"1":[{"w":"וְעַ֖ל","translit":"wə·‘al","strongs":"H5921","morph":"Conj-w | Prep","gloss":"Now"},{"w":"הַחֲתוּמִ֑ים","translit":"ha·ḥă·ṯū·mîm","strongs":"H2856","morph":"Art | V-Qal-QalPassPrtcpl-mp","gloss":"these [were the ones] who sealed [the document]"},{"w":"נְחֶמְיָ֧ה","translit":"nə·ḥem·yāh","strongs":"H5166","morph":"N-proper-ms","gloss":"Nehemiah"},{"w":"הַתִּרְשָׁ֛תָא","translit":"hat·tir·šā·ṯā","strongs":"H8660","morph":"Art | Adj-ms","gloss":"the governor"},{"w":"בֶּן־","translit":"ben-","strongs":"H1121","morph":"N-msc","gloss":"son"},{"w":"חֲכַלְיָ֖ה","translit":"ḥă·ḵal·yāh","strongs":"H2446","morph":"N-proper-ms","gloss":"of Hacaliah"},{"w":"וְצִדְקִיָּֽה׃","translit":"wə·ṣiḏ·qî·yāh","strongs":"H6667","morph":"Conj-w | N-proper-ms","gloss":"and also Zedekiah"}],"2":[{"w":"שְׂרָיָ֥ה","translit":"śə·rā·yāh","strongs":"H8304","morph":"N-proper-ms","gloss":"Seraiah"},{"w":"עֲזַרְיָ֖ה","translit":"‘ă·zar·yāh","strongs":"H5838","morph":"N-proper-ms","gloss":"Azariah"},{"w":"יִרְמְיָֽה׃","translit":"yir·mə·yāh","strongs":"H3414","morph":"N-proper-ms","gloss":"Jeremiah"}],"3":[{"w":"פַּשְׁח֥וּר","translit":"paš·ḥūr","strongs":"H6583","morph":"N-proper-ms","gloss":"Pashhur"},{"w":"אֲמַרְיָ֖ה","translit":"’ă·mar·yāh","strongs":"H568","morph":"N-proper-ms","gloss":"Amariah"},{"w":"מַלְכִּיָּֽה׃","translit":"mal·kî·yāh","strongs":"H4441","morph":"N-proper-ms","gloss":"Malchijah"}],"4":[{"w":"חַטּ֥וּשׁ","translit":"ḥaṭ·ṭūš","strongs":"H2407","morph":"N-proper-ms","gloss":"Hattush"},{"w":"שְׁבַנְיָ֖ה","translit":"šə·ḇan·yāh","strongs":"H7645","morph":"N-proper-ms","gloss":"Shebaniah"},{"w":"מַלּֽוּךְ׃","translit":"mal·lūḵ","strongs":"H4409","morph":"N-proper-ms","gloss":"Malluch"}],"5":[{"w":"חָרִ֥ם","translit":"ḥā·rim","strongs":"H2766","morph":"N-proper-ms","gloss":"Harim"},{"w":"מְרֵמ֖וֹת","translit":"mə·rê·mō·wṯ","strongs":"H4822","morph":"N-proper-ms","gloss":"Meremoth"},{"w":"עֹֽבַדְיָֽה׃","translit":"‘ō·ḇaḏ·yāh","strongs":"H5662","morph":"N-proper-ms","gloss":"Obadiah"}],"6":[{"w":"דָּנִיֵּ֥אל","translit":"dā·nî·yêl","strongs":"H1841","morph":"N-proper-ms","gloss":"Daniel"},{"w":"גִּנְּת֖וֹן","translit":"gin·nə·ṯō·wn","strongs":"H1599","morph":"N-proper-ms","gloss":"Ginnethon"},{"w":"בָּרֽוּךְ׃","translit":"bā·rūḵ","strongs":"H1263","morph":"N-proper-ms","gloss":"Baruch"}],"7":[{"w":"מְשֻׁלָּ֥ם","translit":"mə·šul·lām","strongs":"H4918","morph":"N-proper-ms","gloss":"Meshullam"},{"w":"אֲבִיָּ֖ה","translit":"’ă·ḇî·yāh","strongs":"H29","morph":"N-proper-ms","gloss":"Abijah"},{"w":"מִיָּמִֽן׃","translit":"mî·yā·min","strongs":"H4326","morph":"N-proper-ms","gloss":"Mijamin"}],"8":[{"w":"מַֽעַזְיָ֥ה","translit":"ma·‘az·yāh","strongs":"H4590","morph":"N-proper-ms","gloss":"Maaziah"},{"w":"בִלְגַּ֖י","translit":"ḇil·gay","strongs":"H1084","morph":"N-proper-ms","gloss":"Bilgai"},{"w":"שְׁמַֽעְיָ֑ה","translit":"šə·ma‘·yāh","strongs":"H8098","morph":"N-proper-ms","gloss":"and Shemaiah"},{"w":"אֵ֖לֶּה","translit":"’êl·leh","strongs":"H428","morph":"Pro-cp","gloss":"These [were]"},{"w":"הַכֹּהֲנִֽים׃ס","translit":"hak·kō·hă·nîm","strongs":"H3548","morph":"Art | N-mp","gloss":"the priests"}],"9":[{"w":"וְֽהַלְוִיִּ֑ם","translit":"wə·hal·wî·yim","strongs":"H3881","morph":"Conj-w, Art | N-proper-mp","gloss":"The Levites:"},{"w":"וְיֵשׁ֙וּעַ֙","translit":"wə·yê·šū·a‘","strongs":"H3442","morph":"Conj-w | N-proper-ms","gloss":"Jeshua"},{"w":"בֶּן־","translit":"ben-","strongs":"H1121","morph":"N-msc","gloss":"son"},{"w":"אֲזַנְיָ֔ה","translit":"’ă·zan·yāh","strongs":"H245","morph":"N-proper-ms","gloss":"of Azaniah"},{"w":"בִּנּ֕וּי","translit":"bin·nui","strongs":"H1131","morph":"N-proper-ms","gloss":"Binnui"},{"w":"מִבְּנֵ֥י","translit":"mib·bə·nê","strongs":"H1121","morph":"Prep-m | N-mpc","gloss":"of the sons"},{"w":"חֵנָדָ֖ד","translit":"ḥê·nā·ḏāḏ","strongs":"H2582","morph":"N-proper-ms","gloss":"of Henadad"},{"w":"קַדְמִיאֵֽל׃","translit":"qaḏ·mî·’êl","strongs":"H6934","morph":"N-proper-ms","gloss":"Kadmiel"}],"10":[{"w":"וַאֲחֵיהֶ֑ם","translit":"wa·’ă·ḥê·hem","strongs":"H251","morph":"Conj-w | N-mpc | 3mp","gloss":"and their associates"},{"w":"שְׁבַנְיָ֧ה","translit":"šə·ḇan·yāh","strongs":"H7645","morph":"N-proper-ms","gloss":"Shebaniah"},{"w":"הֽוֹדִיָּ֛ה","translit":"hō·w·ḏî·yāh","strongs":"H1941","morph":"N-proper-ms","gloss":"Hodiah"},{"w":"קְלִיטָ֖א","translit":"qə·lî·ṭā","strongs":"H7042","morph":"N-proper-ms","gloss":"Kelita"},{"w":"פְּלָאיָ֥ה","translit":"pə·lā·yāh","strongs":"H6411","morph":"N-proper-ms","gloss":"Pelaiah"},{"w":"חָנָֽן׃","translit":"ḥā·nān","strongs":"H2605","morph":"N-proper-ms","gloss":"Hanan"}],"11":[{"w":"מִיכָ֥א","translit":"mî·ḵā","strongs":"H4316","morph":"N-proper-ms","gloss":"Mica"},{"w":"רְח֖וֹב","translit":"rə·ḥō·wḇ","strongs":"H7340","morph":"N-proper-ms","gloss":"Rehob"},{"w":"חֲשַׁבְיָֽה׃","translit":"ḥă·šaḇ·yāh","strongs":"H2811","morph":"N-proper-ms","gloss":"Hashabiah"}],"12":[{"w":"זַכּ֥וּר","translit":"zak·kūr","strongs":"H2139","morph":"N-proper-ms","gloss":"Zaccur"},{"w":"שֵׁרֵֽבְיָ֖ה","translit":"šê·rê·ḇə·yāh","strongs":"H8274","morph":"N-proper-ms","gloss":"Sherebiah"},{"w":"שְׁבַנְיָֽה׃","translit":"šə·ḇan·yāh","strongs":"H7645","morph":"N-proper-ms","gloss":"Shebaniah"}],"13":[{"w":"הוֹדִיָּ֥ה","translit":"hō·w·ḏî·yāh","strongs":"H1941","morph":"N-proper-ms","gloss":"Hodiah"},{"w":"בָנִ֖י","translit":"ḇā·nî","strongs":"H1137","morph":"N-proper-ms","gloss":"Bani"},{"w":"בְּנִֽינוּ׃ס","translit":"bə·nî·nū","strongs":"H1148","morph":"N-proper-ms","gloss":"and Beninu"}],"14":[{"w":"רָאשֵׁ֖י","translit":"rā·šê","strongs":"H7218","morph":"N-mpc","gloss":"[And] the leaders"},{"w":"הָעָ֑ם","translit":"hā·‘ām","strongs":"H5971","morph":"Art | N-ms","gloss":"of the people"},{"w":"פַּרְעֹשׁ֙","translit":"par·‘ōš","strongs":"H6551","morph":"N-proper-ms","gloss":"Parosh"},{"w":"פַּחַ֣ת","translit":"pa·ḥaṯ","strongs":"H6355","gloss":"vvv"},{"w":"מוֹאָ֔ב","translit":"mō·w·’āḇ","strongs":"H6355","morph":"N-proper-ms","gloss":"Pahath-moab"},{"w":"עֵילָ֥ם","translit":"‘ê·lām","strongs":"H5867","morph":"N-proper-ms","gloss":"Elam"},{"w":"זַתּ֖וּא","translit":"zat·tū","strongs":"H2240","morph":"N-proper-ms","gloss":"Zattu"},{"w":"בָּנִֽי׃","translit":"bā·nî","strongs":"H1137","morph":"N-proper-ms","gloss":"Bani"}],"15":[{"w":"בֻּנִּ֥י","translit":"bun·nî","strongs":"H1138","morph":"N-proper-ms","gloss":"Bunni"},{"w":"עַזְגָּ֖ד","translit":"‘az·gāḏ","strongs":"H5803","morph":"N-proper-ms","gloss":"Azgad"},{"w":"בֵּבָֽי׃","translit":"bê·ḇāy","strongs":"H893","morph":"N-proper-ms","gloss":"Bebai"}],"16":[{"w":"אֲדֹנִיָּ֥ה","translit":"’ă·ḏō·nî·yāh","strongs":"H138","morph":"N-proper-ms","gloss":"Adonijah"},{"w":"בִגְוַ֖י","translit":"ḇiḡ·way","strongs":"H902","morph":"N-proper-ms","gloss":"Bigvai"},{"w":"עָדִֽין׃","translit":"‘ā·ḏîn","strongs":"H5720","morph":"N-proper-ms","gloss":"Adin"}],"17":[{"w":"אָטֵ֥ר","translit":"’ā·ṭêr","strongs":"H333","morph":"N-proper-ms","gloss":"Ater"},{"w":"חִזְקִיָּ֖ה","translit":"ḥiz·qî·yāh","strongs":"H2396","morph":"N-proper-ms","gloss":"Hezekiah"},{"w":"עַזּֽוּר׃","translit":"‘az·zūr","strongs":"H5809","morph":"N-proper-ms","gloss":"Azzur"}],"18":[{"w":"הוֹדִיָּ֥ה","translit":"hō·w·ḏî·yāh","strongs":"H1941","morph":"N-proper-ms","gloss":"Hodiah"},{"w":"חָשֻׁ֖ם","translit":"ḥā·šum","strongs":"H2828","morph":"N-proper-ms","gloss":"Hashum"},{"w":"בֵּצָֽי׃","translit":"bê·ṣāy","strongs":"H1209","morph":"N-proper-ms","gloss":"Bezai"}],"19":[{"w":"חָרִ֥יף","translit":"ḥā·rîp̄","strongs":"H2756","morph":"N-proper-ms","gloss":"Hariph"},{"w":"עֲנָת֖וֹת","translit":"‘ă·nā·ṯō·wṯ","strongs":"H6068","morph":"N-proper-ms","gloss":"Anathoth"},{"w":"נוֹבָי׃","translit":"nō·ḇå̄y","strongs":"H5109","morph":"N-proper-ms","gloss":"Nebai"}],"20":[{"w":"מַגְפִּיעָ֥שׁ","translit":"maḡ·pî·‘āš","strongs":"H4047","morph":"N-proper-ms","gloss":"Magpiash"},{"w":"מְשֻׁלָּ֖ם","translit":"mə·šul·lām","strongs":"H4918","morph":"N-proper-ms","gloss":"Meshullam"},{"w":"חֵזִֽיר׃","translit":"ḥê·zîr","strongs":"H2387","morph":"N-proper-ms","gloss":"Hezir"}],"21":[{"w":"מְשֵׁיזַבְאֵ֥ל","translit":"mə·šê·zaḇ·’êl","strongs":"H4898","morph":"N-proper-ms","gloss":"Meshezabel"},{"w":"צָד֖וֹק","translit":"ṣā·ḏō·wq","strongs":"H6659","morph":"N-proper-ms","gloss":"Zadok"},{"w":"יַדּֽוּעַ׃","translit":"yad·dū·a‘","strongs":"H3037","morph":"N-proper-ms","gloss":"Jaddua"}],"22":[{"w":"פְּלַטְיָ֥ה","translit":"pə·laṭ·yāh","strongs":"H6410","morph":"N-proper-ms","gloss":"Pelatiah"},{"w":"חָנָ֖ן","translit":"ḥā·nān","strongs":"H2605","morph":"N-proper-ms","gloss":"Hanan"},{"w":"עֲנָיָֽה׃","translit":"‘ă·nā·yāh","strongs":"H6043","morph":"N-proper-ms","gloss":"Anaiah"}],"23":[{"w":"הוֹשֵׁ֥עַ","translit":"hō·wō·šê·a‘","strongs":"H1954","morph":"N-proper-ms","gloss":"Hoshea"},{"w":"חֲנַנְיָ֖ה","translit":"ḥă·nan·yāh","strongs":"H2608","morph":"N-proper-ms","gloss":"Hananiah"},{"w":"חַשּֽׁוּב׃","translit":"ḥaš·šūḇ","strongs":"H2815","morph":"N-proper-ms","gloss":"Hasshub"}],"24":[{"w":"הַלּוֹחֵ֥שׁ","translit":"hal·lō·w·ḥêš","strongs":"H3873","morph":"Art | N-proper-ms","gloss":"Hallohesh"},{"w":"פִּלְחָ֖א","translit":"pil·ḥā","strongs":"H6401","morph":"N-proper-ms","gloss":"Pilha"},{"w":"שׁוֹבֵֽק׃","translit":"šō·w·ḇêq","strongs":"H7733","morph":"N-proper-ms","gloss":"Shobek"}],"25":[{"w":"רְח֥וּם","translit":"rə·ḥūm","strongs":"H7348","morph":"N-proper-ms","gloss":"Rehum"},{"w":"חֲשַׁבְנָ֖ה","translit":"ḥă·šaḇ·nāh","strongs":"H2812","morph":"N-proper-ms","gloss":"Hashabnah"},{"w":"מַעֲשֵׂיָֽה׃","translit":"ma·‘ă·śê·yāh","strongs":"H4641","morph":"N-proper-ms","gloss":"Maaseiah"}],"26":[{"w":"וַאֲחִיָּ֥ה","translit":"wa·’ă·ḥî·yāh","strongs":"H281","morph":"Conj-w | N-proper-ms","gloss":"Ahijah"},{"w":"חָנָ֖ן","translit":"ḥā·nān","strongs":"H2605","morph":"N-proper-ms","gloss":"Hanan"},{"w":"עָנָֽן׃","translit":"‘ā·nān","strongs":"H6052","morph":"N-proper-ms","gloss":"Anan"}],"27":[{"w":"מַלּ֥וּךְ","translit":"mal·lūḵ","strongs":"H4409","morph":"N-proper-ms","gloss":"Malluch"},{"w":"חָרִ֖ם","translit":"ḥā·rim","strongs":"H2766","morph":"N-proper-ms","gloss":"Harim"},{"w":"בַּעֲנָֽה׃","translit":"ba·‘ă·nāh","strongs":"H1196","morph":"N-proper-ms","gloss":"[and] Baanah"}],"28":[{"w":"וּשְׁאָ֣ר","translit":"ū·šə·’ār","strongs":"H7605","morph":"Conj-w | N-msc","gloss":"The rest"},{"w":"הָעָ֡ם","translit":"hā·‘ām","strongs":"H5971","morph":"Art | N-ms","gloss":"of the people"},{"w":"הַכֹּהֲנִ֣ים","translit":"hak·kō·hă·nîm","strongs":"H3548","morph":"Art | N-mp","gloss":"the priests"},{"w":"הַ֠לְוִיִּם","translit":"hal·wî·yim","strongs":"H3881","morph":"Art | N-proper-mp","gloss":"Levites"},{"w":"הַשּׁוֹעֲרִ֨ים","translit":"haš·šō·w·‘ă·rîm","strongs":"H7778","morph":"Art | N-mp","gloss":"gatekeepers"},{"w":"הַמְשֹׁרְרִ֜ים","translit":"ham·šō·rə·rîm","strongs":"H7891","morph":"Art | V-Piel-Prtcpl-mp","gloss":"singers"},{"w":"הַנְּתִינִ֗ים","translit":"han·nə·ṯî·nîm","strongs":"H5411","morph":"Art | N-mp","gloss":"temple servants"},{"w":"וְֽכָל־","translit":"wə·ḵāl","strongs":"H3605","morph":"Conj-w | N-msc","gloss":"and all"},{"w":"הַנִּבְדָּ֞ל","translit":"han·niḇ·dāl","strongs":"H914","morph":"Art | V-Nifal-Prtcpl-ms","gloss":"who had separated themselves"},{"w":"מֵעַמֵּ֤י","translit":"mê·‘am·mê","strongs":"H5971","morph":"Prep-m | N-mpc","gloss":"from the people"},{"w":"הָאֲרָצוֹת֙","translit":"hā·’ă·rā·ṣō·wṯ","strongs":"H776","morph":"Art | N-fp","gloss":"of the land"},{"w":"אֶל־","translit":"’el-","strongs":"H413","morph":"Prep","gloss":"to"},{"w":"תּוֹרַ֣ת","translit":"tō·w·raṯ","strongs":"H8451","morph":"N-fsc","gloss":"obey the Law"},{"w":"הָאֱלֹהִ֔ים","translit":"hā·’ĕ·lō·hîm","strongs":"H430","morph":"Art | N-mp","gloss":"of God"},{"w":"נְשֵׁיהֶ֖ם","translit":"nə·šê·hem","strongs":"H802","morph":"N-fpc | 3mp","gloss":"along with their wives"},{"w":"כֹּ֖ל","translit":"kōl","strongs":"H3605","morph":"N-ms","gloss":"and all"},{"w":"בְּנֵיהֶ֣ם","translit":"bə·nê·hem","strongs":"H1121","morph":"N-mpc | 3mp","gloss":"their sons"},{"w":"וּבְנֹתֵיהֶ֑ם","translit":"ū·ḇə·nō·ṯê·hem","strongs":"H1323","morph":"Conj-w | N-fpc | 3mp","gloss":"and daughters"},{"w":"יוֹדֵ֥עַ","translit":"yō·w·ḏê·a‘","strongs":"H3045","morph":"V-Qal-Prtcpl-ms","gloss":"vvv"},{"w":"מֵבִֽין׃","translit":"mê·ḇîn","strongs":"H995","morph":"V-Hifil-Prtcpl-ms","gloss":"who are able to understand"}],"29":[{"w":"מַחֲזִיקִ֣ים","translit":"ma·ḥă·zî·qîm","strongs":"H2388","morph":"V-Hifil-Prtcpl-mp","gloss":"hereby join"},{"w":"עַל־","translit":"‘al-","strongs":"H5921","morph":"Prep","gloss":"with"},{"w":"אַדִּירֵיהֶם֒","translit":"’ad·dî·rê·hem","strongs":"H117","morph":"N-mpc | 3mp","gloss":"their noble"},{"w":"אֲחֵיהֶם֮","translit":"’ă·ḥê·hem","strongs":"H251","morph":"N-mpc | 3mp","gloss":"brothers"},{"w":"וּבָאִ֞ים","translit":"ū·ḇā·’îm","strongs":"H935","morph":"Conj-w | V-Qal-Prtcpl-mp","gloss":"and commit"},{"w":"וּבִשְׁבוּעָ֗ה","translit":"ū·ḇiš·ḇū·‘āh","strongs":"H7621","morph":"Conj-w, Prep-b | N-fs","gloss":"themselves with a sworn"},{"w":"בְּאָלָ֣ה","translit":"bə·’ā·lāh","strongs":"H423","morph":"Prep-b | N-fs","gloss":"oath"},{"w":"לָלֶ֙כֶת֙","translit":"lā·le·ḵeṯ","strongs":"H1980","morph":"Prep-l | V-Qal-Inf","gloss":"to follow"},{"w":"בְּתוֹרַ֣ת","translit":"bə·ṯō·w·raṯ","strongs":"H8451","morph":"Prep-b | N-fsc","gloss":"the Law"},{"w":"הָאֱלֹהִ֔ים","translit":"hā·’ĕ·lō·hîm","strongs":"H430","morph":"Art | N-mp","gloss":"of God"},{"w":"אֲשֶׁ֣ר","translit":"’ă·šer","strongs":"H834","morph":"Pro-r","gloss":"-"},{"w":"נִתְּנָ֔ה","translit":"nit·tə·nāh","strongs":"H5414","morph":"V-Nifal-Perf-3fs","gloss":"given"},{"w":"בְּיַ֖ד","translit":"bə·yaḏ","strongs":"H3027","morph":"Prep-b | N-fsc","gloss":"through"},{"w":"הָֽאֱלֹהִ֑ים","translit":"hā·’ĕ·lō·hîm","strongs":"H430","morph":"Art | N-mp","gloss":"[His]"},{"w":"עֶֽבֶד־","translit":"‘e·ḇeḏ-","strongs":"H5650","morph":"N-msc","gloss":"servant"},{"w":"מֹשֶׁ֣ה","translit":"mō·šeh","strongs":"H4872","morph":"N-proper-ms","gloss":"Moses"},{"w":"וְלַעֲשׂ֗וֹת","translit":"wə·la·‘ă·śō·wṯ","strongs":"H6213","morph":"Conj-w, Prep-l | V-Qal-Inf","gloss":"and to obey"},{"w":"וְלִשְׁמ֣וֹר","translit":"wə·liš·mō·wr","strongs":"H8104","morph":"Conj-w, Prep-l | V-Qal-Inf","gloss":"carefully"},{"w":"אֶת־","translit":"’eṯ-","strongs":"H853","morph":"DirObjM","gloss":"-"},{"w":"כָּל־","translit":"kāl-","strongs":"H3605","morph":"N-msc","gloss":"all"},{"w":"מִצְוֺת֙","translit":"miṣ·wōṯ","strongs":"H4687","morph":"N-fpc","gloss":"the commandments"},{"w":"וּמִשְׁפָּטָ֖יו","translit":"ū·miš·pā·ṭāw","strongs":"H4941","morph":"Conj-w | N-mpc | 3ms","gloss":"ordinances"},{"w":"וְחֻקָּֽיו׃","translit":"wə·ḥuq·qāw","strongs":"H2706","morph":"Conj-w | N-mpc | 3ms","gloss":"and statutes"},{"w":"יְהוָ֣ה","translit":"Yah·weh","strongs":"H3068","morph":"N-proper-ms","gloss":"of the LORD"},{"w":"אֲדֹנֵ֔ינוּ","translit":"’ă·ḏō·nê·nū","strongs":"H113","morph":"N-mpc | 1cp","gloss":"our Lord"}],"30":[{"w":"וַאֲשֶׁ֛ר","translit":"wa·’ă·šer","strongs":"H834","morph":"Conj-w | Pro-r","gloss":"-"},{"w":"לֹא־","translit":"lō-","strongs":"H3808","morph":"Adv-NegPrt","gloss":"We will not"},{"w":"נִתֵּ֥ן","translit":"nit·tên","strongs":"H5414","morph":"V-Qal-Imperf-1cp","gloss":"give"},{"w":"בְּנֹתֵ֖ינוּ","translit":"bə·nō·ṯê·nū","strongs":"H1323","morph":"N-fpc | 1cp","gloss":"our daughters {in marriage}"},{"w":"לְעַמֵּ֣י","translit":"lə·‘am·mê","strongs":"H5971","morph":"Prep-l | N-mpc","gloss":"to the people"},{"w":"הָאָ֑רֶץ","translit":"hā·’ā·reṣ","strongs":"H776","morph":"Art | N-fs","gloss":"of the land"},{"w":"וְאֶת־","translit":"wə·’eṯ-","strongs":"H853","morph":"Conj-w | DirObjM","gloss":"-"},{"w":"לֹ֥א","translit":"lō","strongs":"H3808","morph":"Adv-NegPrt","gloss":"and we will not"},{"w":"נִקַּ֖ח","translit":"niq·qaḥ","strongs":"H3947","morph":"V-Qal-Imperf-1cp","gloss":"take"},{"w":"בְּנֹ֣תֵיהֶ֔ם","translit":"bə·nō·ṯê·hem","strongs":"H1323","morph":"N-fpc | 3mp","gloss":"their daughters"},{"w":"לְבָנֵֽינוּ׃","translit":"lə·ḇā·nê·nū","strongs":"H1121","morph":"Prep-l | N-mpc | 1cp","gloss":"for our sons"}],"31":[{"w":"וְעַמֵּ֣י","translit":"wə·‘am·mê","strongs":"H5971","morph":"Conj-w | N-mpc","gloss":"When the people"},{"w":"הָאָ֡רֶץ","translit":"hā·’ā·reṣ","strongs":"H776","morph":"Art | N-fs","gloss":"of the land"},{"w":"הַֽמְבִיאִים֩","translit":"ham·ḇî·’îm","strongs":"H935","morph":"Art | V-Hifil-Prtcpl-mp","gloss":"bring"},{"w":"אֶת־","translit":"’eṯ-","strongs":"H853","morph":"DirObjM","gloss":"-"},{"w":"הַמַּקָּח֨וֹת","translit":"ham·maq·qā·ḥō·wṯ","strongs":"H4728","morph":"Art | N-fp","gloss":"merchandise"},{"w":"וְכָל־","translit":"wə·ḵāl","strongs":"H3605","morph":"Conj-w | N-msc","gloss":"or any"},{"w":"שֶׁ֜בֶר","translit":"še·ḇer","strongs":"H7668","morph":"N-ms","gloss":"kind of grain"},{"w":"לִמְכּ֔וֹר","translit":"lim·kō·wr","strongs":"H4376","morph":"Prep-l | V-Qal-Inf","gloss":"to sell"},{"w":"הַשַּׁבָּת֙","translit":"haš·šab·bāṯ","strongs":"H7676","morph":"Art | N-cs","gloss":"on the Sabbath"},{"w":"בְּי֤וֹם","translit":"bə·yō·wm","strongs":"H3117","morph":"Prep-b | N-msc","gloss":"day"},{"w":"לֹא־","translit":"lō-","strongs":"H3808","morph":"Adv-NegPrt","gloss":"we will not"},{"w":"נִקַּ֥ח","translit":"niq·qaḥ","strongs":"H3947","morph":"V-Qal-Imperf-1cp","gloss":"buy"},{"w":"מֵהֶ֛ם","translit":"mê·hem","morph":"Prep-m | Pro-3mp","gloss":"from them"},{"w":"בַּשַּׁבָּ֖ת","translit":"baš·šab·bāṯ","strongs":"H7676","morph":"Prep-b, Art | N-cs","gloss":"on a Sabbath"},{"w":"קֹ֑דֶשׁ","translit":"qō·ḏeš","strongs":"H6944","morph":"N-ms","gloss":"or holy"},{"w":"וּבְי֣וֹם","translit":"ū·ḇə·yō·wm","strongs":"H3117","morph":"Conj-w, Prep-b | N-msc","gloss":"day"},{"w":"הַשְּׁבִיעִ֖ית","translit":"haš·šə·ḇî·‘îṯ","strongs":"H7637","morph":"Art | Number-ofs","gloss":"Every seventh"},{"w":"הַשָּׁנָ֥ה","translit":"haš·šā·nāh","strongs":"H8141","morph":"Art | N-fs","gloss":"year"},{"w":"וְנִטֹּ֛שׁ","translit":"wə·niṭ·ṭōš","strongs":"H5203","morph":"Conj-w | V-Qal-ConjImperf-1cp","gloss":"we will let the fields lie fallow"},{"w":"אֶת־","translit":"’eṯ-","strongs":"H853","morph":"DirObjM","gloss":"-"},{"w":"כָל־","translit":"ḵāl","strongs":"H3605","morph":"N-msc","gloss":"and will cancel every"},{"w":"יָֽד׃","translit":"yāḏ","strongs":"H3027","morph":"N-fs","gloss":". . ."},{"w":"וּמַשָּׁ֥א","translit":"ū·maš·šā","strongs":"H4855","morph":"Conj-w | N-msc","gloss":"debt"}],"32":[{"w":"וְהֶעֱמַ֤דְנוּ","translit":"wə·he·‘ĕ·maḏ·nū","strongs":"H5975","morph":"Conj-w | V-Hifil-ConjPerf-1cp","gloss":"We also place"},{"w":"עָלֵ֛ינוּ","translit":"‘ā·lê·nū","strongs":"H5921","morph":"Prep | 1cp","gloss":"ourselves"},{"w":"עָלֵ֙ינוּ֙","translit":"‘ā·lê·nū","strongs":"H5921","morph":"Prep | 1cp","gloss":"under"},{"w":"מִצְוֺ֔ת","translit":"miṣ·wōṯ","strongs":"H4687","morph":"N-fpc","gloss":"the obligation"},{"w":"לָתֵ֥ת","translit":"lā·ṯêṯ","strongs":"H5414","morph":"Prep-l | V-Qal-Inf","gloss":"to contribute"},{"w":"שְׁלִשִׁ֥ית","translit":"šə·li·šîṯ","strongs":"H7992","morph":"Number-ofsc","gloss":"a third"},{"w":"הַשֶּׁ֖קֶל","translit":"haš·še·qel","strongs":"H8255","morph":"Art | N-ms","gloss":"of a shekel"},{"w":"בַּשָּׁנָ֑ה","translit":"baš·šā·nāh","strongs":"H8141","morph":"Prep-b, Art | N-fs","gloss":"yearly"},{"w":"לַעֲבֹדַ֖ת","translit":"la·‘ă·ḇō·ḏaṯ","strongs":"H5656","morph":"Prep-l | N-fsc","gloss":"for the service"},{"w":"בֵּ֥ית","translit":"bêṯ","strongs":"H1004","morph":"N-msc","gloss":"of the house"},{"w":"אֱלֹהֵֽינוּ׃","translit":"’ĕ·lō·hê·nū","strongs":"H430","morph":"N-mpc | 1cp","gloss":"of our God"}],"33":[{"w":"לְלֶ֣חֶם","translit":"lə·le·ḥem","strongs":"H3899","morph":"Prep-l | N-msc","gloss":"for the showbread"},{"w":"הַֽמַּעֲרֶ֡כֶת","translit":"ham·ma·‘ă·re·ḵeṯ","strongs":"H4635","morph":"Art | N-fs","gloss":". . ."},{"w":"הַתָּמִ֣יד","translit":"hat·tā·mîḏ","strongs":"H8548","morph":"Art | Adv","gloss":"for the regular"},{"w":"וּמִנְחַ֣ת","translit":"ū·min·ḥaṯ","strongs":"H4503","morph":"Conj-w | N-fsc","gloss":"grain offerings"},{"w":"הַ֠תָּמִיד","translit":"hat·tā·mîḏ","strongs":"H8548","morph":"Art | Adv","gloss":"-"},{"w":"וּלְעוֹלַ֣ת","translit":"ū·lə·‘ō·w·laṯ","strongs":"H5930","morph":"Conj-w, Prep-l | N-fsc","gloss":"and burnt offerings"},{"w":"הַשַּׁבָּת֨וֹת","translit":"haš·šab·bā·ṯō·wṯ","strongs":"H7676","morph":"Art | N-cp","gloss":"for the Sabbath offerings"},{"w":"הֶחֳדָשִׁ֜ים","translit":"he·ḥo·ḏā·šîm","strongs":"H2320","morph":"Art | N-mp","gloss":"for the New Moons"},{"w":"לַמּוֹעֲדִ֗ים","translit":"lam·mō·w·‘ă·ḏîm","strongs":"H4150","morph":"Prep-l, Art | N-mp","gloss":"and appointed feasts"},{"w":"וְלַקֳּדָשִׁים֙","translit":"wə·laq·qo·ḏā·šîm","strongs":"H6944","morph":"Conj-w, Prep-l, Art | N-mp","gloss":"for the holy offerings"},{"w":"וְלַ֣חַטָּא֔וֹת","translit":"wə·la·ḥaṭ·ṭā·’ō·wṯ","strongs":"H2403","morph":"Conj-w, Prep-l, Art | N-fp","gloss":"for the sin offerings"},{"w":"לְכַפֵּ֖ר","translit":"lə·ḵap·pêr","strongs":"H3722","morph":"Prep-l | V-Piel-Inf","gloss":"to make atonement"},{"w":"עַל־","translit":"‘al-","strongs":"H5921","morph":"Prep","gloss":"for"},{"w":"יִשְׂרָאֵ֑ל","translit":"yiś·rā·’êl","strongs":"H3478","morph":"N-proper-ms","gloss":"Israel"},{"w":"וְכֹ֖ל","translit":"wə·ḵōl","strongs":"H3605","morph":"Conj-w | N-ms","gloss":"and for all"},{"w":"מְלֶ֥אכֶת","translit":"mə·le·ḵeṯ","strongs":"H4399","morph":"N-fsc","gloss":"the duties"},{"w":"בֵּית־","translit":"bêṯ-","strongs":"H1004","morph":"N-msc","gloss":"of the house"},{"w":"אֱלֹהֵֽינוּ׃ס","translit":"’ĕ·lō·hê·nū","strongs":"H430","morph":"N-mpc | 1cp","gloss":"of our God"}],"34":[{"w":"הִפַּ֜לְנוּ","translit":"hip·pal·nū","strongs":"H5307","morph":"V-Hifil-Perf-1cp","gloss":"We have cast"},{"w":"וְהַגּוֹרָל֨וֹת","translit":"wə·hag·gō·w·rā·lō·wṯ","strongs":"H1486","morph":"Conj-w, Art | N-mp","gloss":"lots"},{"w":"הַכֹּהֲנִ֣ים","translit":"hak·kō·hă·nîm","strongs":"H3548","morph":"Art | N-mp","gloss":"among the priests"},{"w":"הַלְוִיִּם֮","translit":"hal·wî·yim","strongs":"H3881","morph":"Art | N-proper-mp","gloss":"Levites"},{"w":"וְהָעָם֒","translit":"wə·hā·‘ām","strongs":"H5971","morph":"Conj-w, Art | N-ms","gloss":"and people"},{"w":"עַל־","translit":"‘al-","strongs":"H5921","morph":"Prep","gloss":"for"},{"w":"קֻרְבַּ֣ן","translit":"qur·ban","strongs":"H7133","morph":"N-msc","gloss":"the donation"},{"w":"הָעֵצִ֗ים","translit":"hā·‘ê·ṣîm","strongs":"H6086","morph":"Art | N-mp","gloss":"of wood"},{"w":"לְבֵית־","translit":"lə·ḇêṯ-","strongs":"H1004","morph":"Prep-l | N-msc","gloss":"by our families"},{"w":"אֲבֹתֵ֛ינוּ","translit":"’ă·ḇō·ṯê·nū","strongs":"H1","morph":"N-mpc | 1cp","gloss":". . ."},{"w":"מְזֻמָּנִ֖ים","translit":"mə·zum·mā·nîm","strongs":"H2163","morph":"V-Pual-Prtcpl-mp","gloss":"at the appointed"},{"w":"לְעִתִּ֥ים","translit":"lə·‘it·tîm","strongs":"H6256","morph":"Prep-l | N-cp","gloss":"times"},{"w":"שָׁנָ֣ה","translit":"šā·nāh","strongs":"H8141","morph":"N-fs","gloss":"each year"},{"w":"בְשָׁנָ֑ה","translit":"ḇə·šā·nāh","strongs":"H8141","morph":"Prep-b | N-fs","gloss":". . ."},{"w":"לְ֠הָבִיא","translit":"lə·hā·ḇî","strongs":"H935","morph":"Prep-l | V-Hifil-Inf","gloss":"They are to bring it"},{"w":"לְבֵ֨ית","translit":"lə·ḇêṯ","strongs":"H1004","morph":"Prep-l | N-msc","gloss":"to the house"},{"w":"אֱלֹהֵ֧ינוּ","translit":"’ĕ·lō·hê·nū","strongs":"H430","morph":"N-mpc | 1cp","gloss":"of our God"},{"w":"לְבַעֵ֗ר","translit":"lə·ḇa·‘êr","strongs":"H1197","morph":"Prep-l | V-Piel-Inf","gloss":"to burn"},{"w":"עַל־","translit":"‘al-","strongs":"H5921","morph":"Prep","gloss":"on"},{"w":"מִזְבַּח֙","translit":"miz·baḥ","strongs":"H4196","morph":"N-msc","gloss":"the altar"},{"w":"יְהוָ֣ה","translit":"Yah·weh","strongs":"H3068","morph":"N-proper-ms","gloss":"of the LORD"},{"w":"אֱלֹהֵ֔ינוּ","translit":"’ĕ·lō·hê·nū","strongs":"H430","morph":"N-mpc | 1cp","gloss":"our God"},{"w":"כַּכָּת֖וּב","translit":"kak·kā·ṯūḇ","strongs":"H3789","morph":"Prep-k, Art | V-Qal-QalPassPrtcpl-ms","gloss":"as it is written"},{"w":"בַּתּוֹרָֽה׃","translit":"bat·tō·w·rāh","strongs":"H8451","morph":"Prep-b, Art | N-fs","gloss":"in the Law"}],"35":[{"w":"וּלְהָבִ֞יא","translit":"ū·lə·hā·ḇî","strongs":"H935","morph":"Conj-w, Prep-l | V-Hifil-Inf","gloss":"We will also bring"},{"w":"אֶת־","translit":"’eṯ-","strongs":"H853","morph":"DirObjM","gloss":"-"},{"w":"בִּכּוּרֵ֣י","translit":"bik·kū·rê","strongs":"H1061","morph":"N-mpc","gloss":"the firstfruits"},{"w":"אַדְמָתֵ֗נוּ","translit":"’aḏ·mā·ṯê·nū","strongs":"H127","morph":"N-fsc | 1cp","gloss":"of our land"},{"w":"וּבִכּוּרֵ֛י","translit":"ū·ḇik·kū·rê","strongs":"H1061","morph":"Conj-w | N-mpc","gloss":". . ."},{"w":"כָּל־","translit":"kāl-","strongs":"H3605","morph":"N-msc","gloss":"and of every"},{"w":"פְּרִ֥י","translit":"pə·rî","strongs":"H6529","morph":"N-msc","gloss":"fruit"},{"w":"כָל־","translit":"ḵāl","strongs":"H3605","morph":"N-msc","gloss":". . ."},{"w":"עֵ֖ץ","translit":"‘êṣ","strongs":"H6086","morph":"N-ms","gloss":"tree"},{"w":"לְבֵ֖ית","translit":"lə·ḇêṯ","strongs":"H1004","morph":"Prep-l | N-msc","gloss":"to the house"},{"w":"יְהוָֽה׃","translit":"Yah·weh","strongs":"H3068","morph":"N-proper-ms","gloss":"of the LORD"},{"w":"שָׁנָ֣ה","translit":"šā·nāh","strongs":"H8141","morph":"N-fs","gloss":"year"},{"w":"בְשָׁנָ֑ה","translit":"ḇə·šā·nāh","strongs":"H8141","morph":"Prep-b | N-fs","gloss":"by year"}],"36":[{"w":"וְאֶת־","translit":"wə·’eṯ-","strongs":"H853","morph":"Conj-w | DirObjM","gloss":"And"},{"w":"לְהָבִיא֙","translit":"lə·hā·ḇî","strongs":"H935","morph":"Prep-l | V-Hifil-Inf","gloss":"we will bring"},{"w":"בְּכֹר֤וֹת","translit":"bə·ḵō·rō·wṯ","strongs":"H1060","morph":"N-mpc","gloss":"the firstborn"},{"w":"בָּנֵ֙ינוּ֙","translit":"bā·nê·nū","strongs":"H1121","morph":"N-mpc | 1cp","gloss":"of our sons"},{"w":"וּבְהֶמְתֵּ֔ינוּ","translit":"ū·ḇə·hem·tê·nū","strongs":"H929","morph":"Conj-w | N-fsc | 1cp","gloss":"and our livestock"},{"w":"כַּכָּת֖וּב","translit":"kak·kā·ṯūḇ","strongs":"H3789","morph":"Prep-k, Art | V-Qal-QalPassPrtcpl-ms","gloss":"as [it is] written"},{"w":"בַּתּוֹרָ֑ה","translit":"bat·tō·w·rāh","strongs":"H8451","morph":"Prep-b, Art | N-fs","gloss":"in the Law"},{"w":"וְאֶת־","translit":"wə·’eṯ-","strongs":"H853","morph":"Conj-w | DirObjM","gloss":"and"},{"w":"בְּכוֹרֵ֨י","translit":"bə·ḵō·w·rê","strongs":"H1060","morph":"N-mpc","gloss":"[will bring] the firstborn"},{"w":"בְקָרֵ֜ינוּ","translit":"ḇə·qā·rê·nū","strongs":"H1241","morph":"N-mpc | 1cp","gloss":"of our herds"},{"w":"וְצֹאנֵ֗ינוּ","translit":"wə·ṣō·nê·nū","strongs":"H6629","morph":"Conj-w | N-fpc | 1cp","gloss":"and flocks"},{"w":"לְבֵ֣ית","translit":"lə·ḇêṯ","strongs":"H1004","morph":"Prep-l | N-msc","gloss":"to the house"},{"w":"אֱלֹהֵ֔ינוּ","translit":"’ĕ·lō·hê·nū","strongs":"H430","morph":"N-mpc | 1cp","gloss":"of our God"},{"w":"לַכֹּ֣הֲנִ֔ים","translit":"lak·kō·hă·nîm","strongs":"H3548","morph":"Prep-l, Art | N-mp","gloss":"to the priests"},{"w":"הַמְשָׁרְתִ֖ים","translit":"ham·šā·rə·ṯîm","strongs":"H8334","morph":"Art | V-Piel-Prtcpl-mp","gloss":"who minister"},{"w":"בְּבֵ֥ית","translit":"bə·ḇêṯ","strongs":"H1004","morph":"Prep-b | N-msc","gloss":"in the house"},{"w":"אֱלֹהֵֽינוּ׃","translit":"’ĕ·lō·hê·nū","strongs":"H430","morph":"N-mpc | 1cp","gloss":"of our God"}],"37":[{"w":"וְאֶת־","translit":"wə·’eṯ-","strongs":"H853","morph":"Conj-w | DirObjM","gloss":"Moreover"},{"w":"נָבִ֤יא","translit":"nā·ḇî","strongs":"H935","morph":"V-Hifil-Imperf-1cp","gloss":"we will bring"},{"w":"לַכֹּהֲנִים֙","translit":"lak·kō·hă·nîm","strongs":"H3548","morph":"Prep-l, Art | N-mp","gloss":"to the priests"},{"w":"אֶל־","translit":"’el-","strongs":"H413","morph":"Prep","gloss":"at"},{"w":"לִשְׁכ֣וֹת","translit":"liš·ḵō·wṯ","strongs":"H3957","morph":"N-fpc","gloss":"the storerooms"},{"w":"בֵּית־","translit":"bêṯ-","strongs":"H1004","morph":"N-msc","gloss":"of the house"},{"w":"אֱלֹהֵ֔ינוּ","translit":"’ĕ·lō·hê·nū","strongs":"H430","morph":"N-mpc | 1cp","gloss":"of our God"},{"w":"רֵאשִׁ֣ית","translit":"rê·šîṯ","strongs":"H7225","morph":"N-fsc","gloss":"the firstfruits"},{"w":"עֲרִיסֹתֵ֣ינוּ","translit":"‘ă·rî·sō·ṯê·nū","strongs":"H6182","morph":"N-fpc | 1cp","gloss":"of our dough"},{"w":"וּ֠תְרוּמֹתֵינוּ","translit":"ū·ṯə·rū·mō·ṯê·nū","strongs":"H8641","morph":"Conj-w | N-fpc | 1cp","gloss":"of our grain offerings"},{"w":"וּפְרִ֨י","translit":"ū·p̄ə·rî","strongs":"H6529","morph":"Conj-w | N-msc","gloss":"of the fruit"},{"w":"כָל־","translit":"ḵāl","strongs":"H3605","morph":"N-msc","gloss":"of all our"},{"w":"עֵ֜ץ","translit":"‘êṣ","strongs":"H6086","morph":"N-ms","gloss":"trees"},{"w":"תִּיר֣וֹשׁ","translit":"tî·rō·wōš","strongs":"H8492","morph":"N-ms","gloss":"and of our new wine"},{"w":"וְיִצְהָ֗ר","translit":"wə·yiṣ·hār","strongs":"H3323","morph":"Conj-w | N-ms","gloss":"and oil"},{"w":"וּמַעְשַׂ֥ר","translit":"ū·ma‘·śar","strongs":"H4643","morph":"Conj-w | N-msc","gloss":"A tenth"},{"w":"אַדְמָתֵ֖נוּ","translit":"’aḏ·mā·ṯê·nū","strongs":"H127","morph":"N-fsc | 1cp","gloss":"of our produce"},{"w":"לַלְוִיִּ֑ם","translit":"lal·wî·yim","strongs":"H3881","morph":"Prep-l | N-proper-mp","gloss":"belongs to the Levites"},{"w":"וְהֵם֙","translit":"wə·hêm","strongs":"H1992","morph":"Conj-w | Pro-3mp","gloss":"so that they"},{"w":"הַלְוִיִּ֔ם","translit":"hal·wî·yim","strongs":"H3881","morph":"Art | N-proper-mp","gloss":". . ."},{"w":"הַֽמְעַשְּׂרִ֔ים","translit":"ham·‘aś·śə·rîm","strongs":"H6237","morph":"Art | V-Piel-Prtcpl-mp","gloss":"shall receive tithes"},{"w":"בְּכֹ֖ל","translit":"bə·ḵōl","strongs":"H3605","morph":"Prep-b | N-msc","gloss":"in all"},{"w":"עָרֵ֥י","translit":"‘ā·rê","strongs":"H5892","morph":"N-fpc","gloss":"the towns"},{"w":"עֲבֹדָתֵֽנוּ׃","translit":"‘ă·ḇō·ḏā·ṯê·nū","strongs":"H5656","morph":"N-fsc | 1cp","gloss":"where we labor"}],"38":[{"w":"הַכֹּהֵ֧ן","translit":"hak·kō·hên","strongs":"H3548","morph":"Art | N-ms","gloss":"A priest"},{"w":"אַהֲרֹ֛ן","translit":"’a·hă·rōn","strongs":"H175","morph":"N-proper-ms","gloss":"of Aaron’s"},{"w":"בֶּֽן־","translit":"ben-","strongs":"H1121","morph":"N-msc","gloss":"line"},{"w":"וְהָיָ֨ה","translit":"wə·hā·yāh","strongs":"H1961","morph":"Conj-w | V-Qal-ConjPerf-3ms","gloss":"is to accompany"},{"w":"עִם־","translit":"‘im-","strongs":"H5973","morph":"Prep","gloss":". . ."},{"w":"הַלְוִיִּ֖ם","translit":"hal·wî·yim","strongs":"H3881","morph":"Art | N-proper-mp","gloss":"the Levites"},{"w":"הַלְוִיִּ֑ם","translit":"hal·wî·yim","strongs":"H3881","morph":"Art | N-proper-mp","gloss":"when they"},{"w":"בַּעְשֵׂ֣ר","translit":"ba‘·śêr","strongs":"H6237","morph":"Prep-b | V-Piel-Inf","gloss":"collect the tenth"},{"w":"וְהַלְוִיִּ֞ם","translit":"wə·hal·wî·yim","strongs":"H3881","morph":"Conj-w, Art | N-proper-mp","gloss":"and the Levites"},{"w":"יַעֲל֨וּ","translit":"ya·‘ă·lū","strongs":"H5927","morph":"V-Hifil-Imperf-3mp","gloss":"are to bring"},{"w":"אֶת־","translit":"’eṯ-","strongs":"H853","morph":"DirObjM","gloss":"-"},{"w":"מַעֲשַׂ֤ר","translit":"ma·‘ă·śar","strongs":"H4643","morph":"N-msc","gloss":"a tenth"},{"w":"הַֽמַּעֲשֵׂר֙","translit":"ham·ma·‘ă·śêr","strongs":"H4643","morph":"Art | N-ms","gloss":"of these tithes"},{"w":"אֶל־","translit":"’el-","strongs":"H413","morph":"Prep","gloss":"to"},{"w":"הַלְּשָׁכ֖וֹת","translit":"hal·lə·šā·ḵō·wṯ","strongs":"H3957","morph":"Art | N-fp","gloss":"the storerooms"},{"w":"לְבֵ֣ית","translit":"lə·ḇêṯ","strongs":"H1004","morph":"Prep-l | N-msc","gloss":"of the treasury"},{"w":"הָאוֹצָֽר׃","translit":"hā·’ō·w·ṣār","strongs":"H214","morph":"Art | N-ms","gloss":". . ."},{"w":"לְבֵ֥ית","translit":"lə·ḇêṯ","strongs":"H1004","morph":"Prep-l | N-msc","gloss":"in the house"},{"w":"אֱלֹהֵ֔ינוּ","translit":"’ĕ·lō·hê·nū","strongs":"H430","morph":"N-mpc | 1cp","gloss":"of our God"}],"39":[{"w":"כִּ֣י","translit":"kî","strongs":"H3588","morph":"Conj","gloss":"For"},{"w":"בְנֵי־","translit":"ḇə·nê-","strongs":"H1121","morph":"N-mpc","gloss":"the Israelites"},{"w":"יִשְׂרָאֵ֜ל","translit":"yiś·rā·’êl","strongs":"H3478","morph":"N-proper-ms","gloss":". . ."},{"w":"וּבְנֵ֣י","translit":"ū·ḇə·nê","strongs":"H1121","morph":"Conj-w | N-mpc","gloss":"and the Levites"},{"w":"הַלֵּוִ֗י","translit":"hal·lê·wî","strongs":"H3878","morph":"Art | N-proper-ms","gloss":". . ."},{"w":"אֶת־","translit":"’eṯ-","strongs":"H853","morph":"DirObjM","gloss":"-"},{"w":"יָבִ֨יאוּ","translit":"yā·ḇî·’ū","strongs":"H935","morph":"V-Hifil-Imperf-3mp","gloss":"are to bring"},{"w":"תְּרוּמַ֣ת","translit":"tə·rū·maṯ","strongs":"H8641","morph":"N-fsc","gloss":"the contributions"},{"w":"הַדָּגָן֮","translit":"had·dā·ḡān","strongs":"H1715","morph":"Art | N-ms","gloss":"of grain"},{"w":"הַתִּיר֣וֹשׁ","translit":"hat·tî·rō·wōš","strongs":"H8492","morph":"Art | N-ms","gloss":"new wine"},{"w":"וְהַיִּצְהָר֒","translit":"wə·hay·yiṣ·hār","strongs":"H3323","morph":"Conj-w, Art | N-ms","gloss":"and oil"},{"w":"אֶל־","translit":"’el-","strongs":"H413","morph":"Prep","gloss":"to"},{"w":"הַ֠לְּשָׁכוֹת","translit":"hal·lə·šā·ḵō·wṯ","strongs":"H3957","morph":"Art | N-fp","gloss":"the storerooms"},{"w":"וְשָׁם֙","translit":"wə·šām","strongs":"H8033","morph":"Conj-w | Adv","gloss":"where"},{"w":"כְּלֵ֣י","translit":"kə·lê","strongs":"H3627","morph":"N-mpc","gloss":"the articles"},{"w":"הַמִּקְדָּ֔שׁ","translit":"ham·miq·dāš","strongs":"H4720","morph":"Art | N-ms","gloss":"of the sanctuary [are kept]"},{"w":"הַמְשָׁ֣רְתִ֔ים","translit":"ham·šā·rə·ṯîm","strongs":"H8334","morph":"Art | V-Piel-Prtcpl-mp","gloss":"and where the ministering"},{"w":"וְהַכֹּהֲנִים֙","translit":"wə·hak·kō·hă·nîm","strongs":"H3548","morph":"Conj-w, Art | N-mp","gloss":"priests"},{"w":"וְהַשּׁוֹעֲרִ֖ים","translit":"wə·haš·šō·w·‘ă·rîm","strongs":"H7778","morph":"Conj-w, Art | N-mp","gloss":"the gatekeepers"},{"w":"וְהַמְשֹׁרְרִ֑ים","translit":"wə·ham·šō·rə·rîm","strongs":"H7891","morph":"Conj-w, Art | V-Piel-Prtcpl-mp","gloss":"and the singers [stay]"},{"w":"וְלֹ֥א","translit":"wə·lō","strongs":"H3808","morph":"Conj-w | Adv-NegPrt","gloss":"Thus we will not"},{"w":"נַעֲזֹ֖ב","translit":"na·‘ă·zōḇ","strongs":"H5800","morph":"V-Qal-Imperf-1cp","gloss":"neglect"},{"w":"אֶת־","translit":"’eṯ-","strongs":"H853","morph":"DirObjM","gloss":"-"},{"w":"בֵּ֥ית","translit":"bêṯ","strongs":"H1004","morph":"N-msc","gloss":"the house"},{"w":"אֱלֹהֵֽינוּ׃","translit":"’ĕ·lō·hê·nū","strongs":"H430","morph":"N-mpc | 1cp","gloss":"of our God"}]}}