{"verses":{"1":[{"w":"וַיְהִ֗י","translit":"way·hî","strongs":"H1961","morph":"Conj-w | V-Qal-ConsecImperf-3ms","gloss":"Now"},{"w":"אַחֲרֵ֛י","translit":"’a·ḥă·rê","strongs":"H310","morph":"Prep","gloss":"after"},{"w":"מ֥וֹת","translit":"mō·wṯ","strongs":"H4194","morph":"N-msc","gloss":"the death"},{"w":"יְהוָ֑ה","translit":"Yah·weh","strongs":"H3068","morph":"N-proper-ms","gloss":"of His"},{"w":"עֶ֣בֶד","translit":"‘e·ḇeḏ","strongs":"H5650","morph":"N-msc","gloss":"servant"},{"w":"מֹשֶׁ֖ה","translit":"mō·šeh","strongs":"H4872","morph":"N-proper-ms","gloss":"Moses"},{"w":"יְהוָה֙","translit":"Yah·weh","strongs":"H3068","morph":"N-proper-ms","gloss":"the LORD"},{"w":"וַיֹּ֤אמֶר","translit":"way·yō·mer","strongs":"H559","morph":"Conj-w | V-Qal-ConsecImperf-3ms","gloss":"spoke"},{"w":"אֶל־","translit":"’el-","strongs":"H413","morph":"Prep","gloss":"to"},{"w":"יְהוֹשֻׁ֣עַ","translit":"yə·hō·wō·šu·a‘","strongs":"H3091","morph":"N-proper-ms","gloss":"Joshua"},{"w":"בִּן־","translit":"bin-","strongs":"H1121","morph":"N-msc","gloss":"son"},{"w":"נ֔וּן","translit":"nūn","strongs":"H5126","morph":"N-proper-ms","gloss":"of Nun"},{"w":"מֹשֶׁ֖ה","translit":"mō·šeh","strongs":"H4872","morph":"N-proper-ms","gloss":"Moses’"},{"w":"מְשָׁרֵ֥ת","translit":"mə·šā·rêṯ","strongs":"H8334","morph":"V-Piel-Prtcpl-msc","gloss":"assistant"},{"w":"לֵאמֹֽר׃","translit":"lê·mōr","strongs":"H559","morph":"Prep-l | V-Qal-Inf","gloss":"saying"}],"2":[{"w":"מֹשֶׁ֥ה","translit":"mō·šeh","strongs":"H4872","morph":"N-proper-ms","gloss":"Moses"},{"w":"עַבְדִּ֖י","translit":"‘aḇ·dî","strongs":"H5650","morph":"N-msc | 1cs","gloss":"My servant"},{"w":"מֵ֑ת","translit":"mêṯ","strongs":"H4191","morph":"V-Qal-Perf-3ms","gloss":"is dead"},{"w":"וְעַתָּה֩","translit":"wə·‘at·tāh","strongs":"H6258","morph":"Conj-w | Adv","gloss":"Now therefore"},{"w":"ק֨וּם","translit":"qūm","strongs":"H6965","morph":"V-Qal-Imp-ms","gloss":"arise"},{"w":"אַתָּה֙","translit":"’at·tāh","strongs":"H859","morph":"Pro-2ms","gloss":"you"},{"w":"וְכָל־","translit":"wə·ḵāl","strongs":"H3605","morph":"Conj-w | N-msc","gloss":"and all"},{"w":"הָעָ֣ם","translit":"hā·‘ām","strongs":"H5971","morph":"Art | N-ms","gloss":"these people"},{"w":"עֲבֹ֜ר","translit":"‘ă·ḇōr","strongs":"H5674","morph":"V-Qal-Imp-ms","gloss":"[and] cross over"},{"w":"אֶת־","translit":"’eṯ-","strongs":"H853","morph":"DirObjM","gloss":"-"},{"w":"הַיַּרְדֵּ֣ן","translit":"hay·yar·dên","strongs":"H3383","morph":"Art | N-proper-fs","gloss":"the Jordan"},{"w":"הַזֶּ֗ה","translit":"haz·zeh","strongs":"H2088","morph":"Art | Pro-ms","gloss":"-"},{"w":"הַזֶּ֔ה","translit":"haz·zeh","strongs":"H2088","morph":"Art | Pro-ms","gloss":"-"},{"w":"אֶל־","translit":"’el-","strongs":"H413","morph":"Prep","gloss":"into"},{"w":"הָאָ֕רֶץ","translit":"hā·’ā·reṣ","strongs":"H776","morph":"Art | N-fs","gloss":"the land"},{"w":"אֲשֶׁ֧ר","translit":"’ă·šer","strongs":"H834","morph":"Pro-r","gloss":"that"},{"w":"אָנֹכִ֛י","translit":"’ā·nō·ḵî","strongs":"H595","morph":"Pro-1cs","gloss":"I"},{"w":"נֹתֵ֥ן","translit":"nō·ṯên","strongs":"H5414","morph":"V-Qal-Prtcpl-ms","gloss":"am giving"},{"w":"לָהֶ֖ם","translit":"lā·hem","morph":"Prep | 3mp","gloss":"to"},{"w":"לִבְנֵ֥י","translit":"liḇ·nê","strongs":"H1121","morph":"Prep-l | N-mpc","gloss":"the children"},{"w":"יִשְׂרָאֵֽל׃","translit":"yiś·rā·’êl","strongs":"H3478","morph":"N-proper-ms","gloss":"of Israel"}],"3":[{"w":"נְתַתִּ֑יו","translit":"nə·ṯat·tîw","strongs":"H5414","morph":"V-Qal-Perf-1cs | 3ms","gloss":"I have given you"},{"w":"כָּל־","translit":"kāl-","strongs":"H3605","morph":"N-msc","gloss":"every"},{"w":"מָק֗וֹם","translit":"mā·qō·wm","strongs":"H4725","morph":"N-ms","gloss":"place"},{"w":"אֲשֶׁ֨ר","translit":"’ă·šer","strongs":"H834","morph":"Pro-r","gloss":"where"},{"w":"כַּֽף־","translit":"kap̄-","strongs":"H3709","morph":"N-fsc","gloss":"the sole"},{"w":"רַגְלְכֶ֛ם","translit":"raḡ·lə·ḵem","strongs":"H7272","morph":"N-fsc | 2mp","gloss":"of your foot"},{"w":"בּ֖וֹ","translit":"bōw","morph":"Prep | 3ms"},{"w":"לָכֶ֣ם","translit":"lā·ḵem","morph":"Prep | 2mp"},{"w":"תִּדְרֹ֧ךְ","translit":"tiḏ·rōḵ","strongs":"H1869","morph":"V-Qal-Imperf-3fs","gloss":"will tread"},{"w":"כַּאֲשֶׁ֥ר","translit":"ka·’ă·šer","strongs":"H834","morph":"Prep-k | Pro-r","gloss":"just as"},{"w":"דִּבַּ֖רְתִּי","translit":"dib·bar·tî","strongs":"H1696","morph":"V-Piel-Perf-1cs","gloss":"I promised"},{"w":"אֶל־","translit":"’el-","strongs":"H413","morph":"Prep","gloss":"to"},{"w":"מֹשֶֽׁה׃","translit":"mō·šeh","strongs":"H4872","morph":"N-proper-ms","gloss":"Moses"}],"4":[{"w":"גְּבוּלְכֶֽם׃","translit":"gə·ḇū·lə·ḵem","strongs":"H1366","morph":"N-msc | 2mp","gloss":"Your territory"},{"w":"יִֽהְיֶ֖ה","translit":"yih·yeh","strongs":"H1961","morph":"V-Qal-Imperf-3ms","gloss":"shall extend"},{"w":"מֵהַמִּדְבָּר֩","translit":"mê·ham·miḏ·bār","strongs":"H4057","morph":"Prep-m, Art | N-ms","gloss":"from the wilderness"},{"w":"וְהַלְּבָנ֨וֹן","translit":"wə·hal·lə·ḇā·nō·wn","strongs":"H3844","morph":"Conj-w, Art | N-proper-fs","gloss":"and Lebanon"},{"w":"הַזֶּ֜ה","translit":"haz·zeh","strongs":"H2088","morph":"Art | Pro-ms","gloss":". . ."},{"w":"וְֽעַד־","translit":"wə·‘aḏ-","strongs":"H5704","morph":"Conj-w | Prep","gloss":"to"},{"w":"הַגָּד֣וֹל","translit":"hag·gā·ḏō·wl","strongs":"H1419","morph":"Art | Adj-ms","gloss":"the great"},{"w":"נְהַר־","translit":"nə·har-","strongs":"H5104","morph":"N-msc","gloss":"River"},{"w":"פְּרָ֗ת","translit":"pə·rāṯ","strongs":"H6578","morph":"N-proper-fs","gloss":"Euphrates"},{"w":"הַנָּהָ֧ר","translit":"han·nā·hār","strongs":"H5104","morph":"Art | N-ms","gloss":"-"},{"w":"כֹּ֚ל","translit":"kōl","strongs":"H3605","morph":"N-msc","gloss":"all"},{"w":"אֶ֣רֶץ","translit":"’e·reṣ","strongs":"H776","morph":"N-fsc","gloss":"the land"},{"w":"הַֽחִתִּ֔ים","translit":"ha·ḥit·tîm","strongs":"H2850","morph":"Art | N-proper-mp","gloss":"of the Hittites"},{"w":"מְב֣וֹא","translit":"mə·ḇō·w","strongs":"H3996","morph":"N-msc","gloss":"and west"},{"w":"הַשָּׁ֑מֶשׁ","translit":"haš·šā·meš","strongs":"H8121","morph":"Art | N-cs","gloss":". . ."},{"w":"וְעַד־","translit":"wə·‘aḏ-","strongs":"H5704","morph":"Conj-w | Prep","gloss":"as far as"},{"w":"הַגָּד֖וֹל","translit":"hag·gā·ḏō·wl","strongs":"H1419","morph":"Art | Adj-ms","gloss":"the Great"},{"w":"הַיָּ֥ם","translit":"hay·yām","strongs":"H3220","morph":"Art | N-ms","gloss":"Sea"}],"5":[{"w":"לֹֽא־","translit":"lō-","strongs":"H3808","morph":"Adv-NegPrt","gloss":"No"},{"w":"אִישׁ֙","translit":"’îš","strongs":"H376","morph":"N-ms","gloss":"one"},{"w":"יִתְיַצֵּ֥ב","translit":"yiṯ·yaṣ·ṣêḇ","strongs":"H3320","morph":"V-Hitpael-Imperf-3ms","gloss":"shall stand"},{"w":"לְפָנֶ֔יךָ","translit":"lə·p̄ā·ne·ḵā","strongs":"H6440","morph":"Prep-l | N-cpc | 2ms","gloss":"against you"},{"w":"כֹּ֖ל","translit":"kōl","strongs":"H3605","morph":"N-msc","gloss":"all"},{"w":"יְמֵ֣י","translit":"yə·mê","strongs":"H3117","morph":"N-mpc","gloss":"the days"},{"w":"חַיֶּ֑יךָ","translit":"ḥay·ye·ḵā","strongs":"H2416","morph":"N-mpc | 2ms","gloss":"of your life"},{"w":"כַּֽאֲשֶׁ֨ר","translit":"ka·’ă·šer","strongs":"H834","morph":"Prep-k | Pro-r","gloss":"As"},{"w":"אֶהְיֶ֣ה","translit":"’eh·yeh","strongs":"H1961","morph":"V-Qal-Imperf-1cs","gloss":"I was"},{"w":"עִמָּ֔ךְ","translit":"‘im·māḵ","strongs":"H5973","morph":"Prep | 2fs","gloss":"with"},{"w":"מֹשֶׁה֙","translit":"mō·šeh","strongs":"H4872","morph":"N-proper-ms","gloss":"Moses"},{"w":"הָיִ֤יתִי","translit":"hā·yî·ṯî","strongs":"H1961","morph":"V-Qal-Perf-1cs","gloss":"so will I be"},{"w":"עִם־","translit":"‘im-","strongs":"H5973","morph":"Prep","gloss":"with you"},{"w":"לֹ֥א","translit":"lō","strongs":"H3808","morph":"Adv-NegPrt","gloss":"I will never"},{"w":"אַרְפְּךָ֖","translit":"’ar·pə·ḵā","strongs":"H7503","morph":"V-Hifil-Imperf-1cs | 2ms","gloss":"leave you"},{"w":"וְלֹ֥א","translit":"wə·lō","strongs":"H3808","morph":"Conj-w | Adv-NegPrt","gloss":"nor"},{"w":"אֶעֶזְבֶֽךָּ׃","translit":"’e·‘ez·ḇe·kā","strongs":"H5800","morph":"V-Qal-Imperf-1cs | 2ms","gloss":"forsake you"}],"6":[{"w":"חֲזַ֖ק","translit":"ḥă·zaq","strongs":"H2388","morph":"V-Qal-Imp-ms","gloss":"Be strong"},{"w":"וֶאֱמָ֑ץ","translit":"we·’ĕ·māṣ","strongs":"H553","morph":"Conj-w | V-Qal-Imp-ms","gloss":"and courageous"},{"w":"כִּ֣י","translit":"kî","strongs":"H3588","morph":"Conj","gloss":"for"},{"w":"אַתָּ֗ה","translit":"’at·tāh","strongs":"H859","morph":"Pro-2ms","gloss":"you"},{"w":"תַּנְחִיל֙","translit":"tan·ḥîl","strongs":"H5157","morph":"V-Hifil-Imperf-2ms","gloss":"shall give these people the inheritance"},{"w":"אֶת־","translit":"’eṯ-","strongs":"H853","morph":"DirObjM","gloss":"-"},{"w":"הָעָ֣ם","translit":"hā·‘ām","strongs":"H5971","morph":"Art | N-ms","gloss":"-"},{"w":"הַזֶּ֔ה","translit":"haz·zeh","strongs":"H2088","morph":"Art | Pro-ms","gloss":". . ."},{"w":"אֶת־","translit":"’eṯ-","strongs":"H853","morph":"DirObjM","gloss":"-"},{"w":"הָאָ֕רֶץ","translit":"hā·’ā·reṣ","strongs":"H776","morph":"Art | N-fs","gloss":"of the land"},{"w":"אֲשֶׁר־","translit":"’ă·šer-","strongs":"H834","morph":"Pro-r","gloss":"that"},{"w":"נִשְׁבַּ֥עְתִּי","translit":"niš·ba‘·tî","strongs":"H7650","morph":"V-Nifal-Perf-1cs","gloss":"I swore"},{"w":"לַאֲבוֹתָ֖ם","translit":"la·’ă·ḇō·w·ṯām","strongs":"H1","morph":"Prep-l | N-mpc | 3mp","gloss":"to their fathers"},{"w":"לָתֵ֥ת","translit":"lā·ṯêṯ","strongs":"H5414","morph":"Prep-l | V-Qal-Inf","gloss":"I would give"},{"w":"לָהֶֽם׃","translit":"lā·hem","morph":"Prep | 3mp","gloss":"them"}],"7":[{"w":"רַק֩","translit":"raq","strongs":"H7535","morph":"Adv","gloss":"Above all"},{"w":"חֲזַ֨ק","translit":"ḥă·zaq","strongs":"H2388","morph":"V-Qal-Imp-ms","gloss":"be strong"},{"w":"מְאֹ֗ד","translit":"mə·’ōḏ","strongs":"H3966","morph":"Adv","gloss":"and very"},{"w":"וֶֽאֱמַ֜ץ","translit":"we·’ĕ·maṣ","strongs":"H553","morph":"Conj-w | V-Qal-Imp-ms","gloss":"courageous"},{"w":"לִשְׁמֹ֤ר","translit":"liš·mōr","strongs":"H8104","morph":"Prep-l | V-Qal-Inf","gloss":"Be careful"},{"w":"לַעֲשׂוֹת֙","translit":"la·‘ă·śō·wṯ","strongs":"H6213","morph":"Prep-l | V-Qal-Inf","gloss":"to observe"},{"w":"כְּכָל־","translit":"kə·ḵāl-","strongs":"H3605","morph":"Prep-k | N-msc","gloss":"all"},{"w":"הַתּוֹרָ֗ה","translit":"hat·tō·w·rāh","strongs":"H8451","morph":"Art | N-fs","gloss":"the law"},{"w":"אֲשֶׁ֤ר","translit":"’ă·šer","strongs":"H834","morph":"Pro-r","gloss":"that"},{"w":"עַבְדִּ֔י","translit":"‘aḇ·dî","strongs":"H5650","morph":"N-msc | 1cs","gloss":"My servant"},{"w":"מֹשֶׁ֣ה","translit":"mō·šeh","strongs":"H4872","morph":"N-proper-ms","gloss":"Moses"},{"w":"צִוְּךָ֙","translit":"ṣiw·wə·ḵā","strongs":"H6680","morph":"V-Piel-Perf-3ms | 2ms","gloss":"commanded you"},{"w":"אַל־","translit":"’al-","strongs":"H408","morph":"Adv","gloss":"Do not"},{"w":"תָּס֥וּר","translit":"tā·sūr","strongs":"H5493","morph":"V-Qal-Imperf-2ms","gloss":"turn"},{"w":"מִמֶּ֖נּוּ","translit":"mim·men·nū","strongs":"H4480","morph":"Prep | 3ms","gloss":"from"},{"w":"יָמִ֣ין","translit":"yā·mîn","strongs":"H3225","morph":"N-fs","gloss":"it to the right"},{"w":"וּשְׂמֹ֑אול","translit":"ū·śə·mō·wl","strongs":"H8040","morph":"Conj-w | N-ms","gloss":"or to the left"},{"w":"לְמַ֣עַן","translit":"lə·ma·‘an","strongs":"H4616","morph":"Conj","gloss":"so that"},{"w":"תַּשְׂכִּ֔יל","translit":"taś·kîl","strongs":"H7919","morph":"V-Hifil-Imperf-2ms","gloss":"you may prosper"},{"w":"בְּכֹ֖ל","translit":"bə·ḵōl","strongs":"H3605","morph":"Prep-b | N-ms","gloss":"wherever"},{"w":"אֲשֶׁ֥ר","translit":"’ă·šer","strongs":"H834","morph":"Pro-r","gloss":". . ."},{"w":"תֵּלֵֽךְ׃","translit":"tê·lêḵ","strongs":"H1980","morph":"V-Qal-Imperf-2ms","gloss":"you go"}],"8":[{"w":"הַזֶּ֜ה","translit":"haz·zeh","strongs":"H2088","morph":"Art | Pro-ms","gloss":"This"},{"w":"סֵפֶר֩","translit":"sê·p̄er","strongs":"H5612","morph":"N-msc","gloss":"Book"},{"w":"הַתּוֹרָ֨ה","translit":"hat·tō·w·rāh","strongs":"H8451","morph":"Art | N-fs","gloss":"of the Law"},{"w":"לֹֽא־","translit":"lō-","strongs":"H3808","morph":"Adv-NegPrt","gloss":"must not"},{"w":"יָמ֡וּשׁ","translit":"yā·mūš","strongs":"H4185","morph":"V-Qal-Imperf-3ms","gloss":"depart"},{"w":"מִפִּ֗יךָ","translit":"mip·pî·ḵā","strongs":"H6310","morph":"Prep-m | N-msc | 2ms","gloss":"from your mouth"},{"w":"וְהָגִ֤יתָ","translit":"wə·hā·ḡî·ṯā","strongs":"H1897","morph":"Conj-w | V-Qal-ConjPerf-2ms","gloss":"meditate"},{"w":"בּוֹ֙","translit":"bōw","morph":"Prep | 3ms","gloss":"on it"},{"w":"יוֹמָ֣ם","translit":"yō·w·mām","strongs":"H3119","morph":"Adv","gloss":"day"},{"w":"וָלַ֔יְלָה","translit":"wā·lay·lāh","strongs":"H3915","morph":"Conj-w | N-ms","gloss":"and night"},{"w":"לְמַ֙עַן֙","translit":"lə·ma·‘an","strongs":"H4616","morph":"Conj","gloss":"so that"},{"w":"תִּשְׁמֹ֣ר","translit":"tiš·mōr","strongs":"H8104","morph":"V-Qal-Imperf-2ms","gloss":"you may be careful"},{"w":"לַעֲשׂ֔וֹת","translit":"la·‘ă·śō·wṯ","strongs":"H6213","morph":"Prep-l | V-Qal-Inf","gloss":"to do"},{"w":"כְּכָל־","translit":"kə·ḵāl-","strongs":"H3605","morph":"Prep-k | N-msc","gloss":"everything"},{"w":"הַכָּת֖וּב","translit":"hak·kā·ṯūḇ","strongs":"H3789","morph":"Art | V-Qal-QalPassPrtcpl-ms","gloss":"written"},{"w":"בּ֑וֹ","translit":"bōw","morph":"Prep | 3ms","gloss":"in it"},{"w":"כִּי־","translit":"kî-","strongs":"H3588","morph":"Conj","gloss":"For"},{"w":"אָ֛ז","translit":"’āz","strongs":"H227","morph":"Adv","gloss":"then"},{"w":"תַּצְלִ֥יחַ","translit":"taṣ·lî·aḥ","strongs":"H6743","morph":"V-Hifil-Imperf-2ms","gloss":"you will prosper"},{"w":"אֶת־","translit":"’eṯ-","strongs":"H853","morph":"DirObjM","gloss":"-"},{"w":"תַּשְׂכִּֽיל׃","translit":"taś·kîl","strongs":"H7919","morph":"V-Hifil-Imperf-2ms","gloss":"and succeed"},{"w":"דְּרָכֶ֖ךָ","translit":"də·rā·ḵe·ḵā","strongs":"H1870","morph":"N-cpc | 2ms","gloss":"in all you do"},{"w":"וְאָ֥ז","translit":"wə·’āz","strongs":"H227","morph":"Conj-w | Adv","gloss":". . ."}],"9":[{"w":"הֲל֤וֹא","translit":"hă·lō·w","strongs":"H3808","morph":"Adv-NegPrt","gloss":"Have I not"},{"w":"צִוִּיתִ֙יךָ֙","translit":"ṣiw·wî·ṯî·ḵā","strongs":"H6680","morph":"V-Piel-Perf-1cs | 2ms","gloss":"commanded you"},{"w":"חֲזַ֣ק","translit":"ḥă·zaq","strongs":"H2388","morph":"V-Qal-Imp-ms","gloss":"to be strong"},{"w":"וֶאֱמָ֔ץ","translit":"we·’ĕ·māṣ","strongs":"H553","morph":"Conj-w | V-Qal-Imp-ms","gloss":"and courageous"},{"w":"אַֽל־","translit":"’al-","strongs":"H408","morph":"Adv","gloss":"Do not"},{"w":"תַּעֲרֹ֖ץ","translit":"ta·‘ă·rōṣ","strongs":"H6206","morph":"V-Qal-Imperf-2ms","gloss":"be afraid"},{"w":"וְאַל־","translit":"wə·’al-","strongs":"H408","morph":"Conj-w | Adv","gloss":". . ."},{"w":"תֵּחָ֑ת","translit":"tê·ḥāṯ","strongs":"H2865","morph":"V-Nifal-Imperf-2ms","gloss":"do not be discouraged"},{"w":"כִּ֤י","translit":"kî","strongs":"H3588","morph":"Conj","gloss":"for"},{"w":"יְהוָ֣ה","translit":"Yah·weh","strongs":"H3068","morph":"N-proper-ms","gloss":"the LORD"},{"w":"אֱלֹהֶ֔יךָ","translit":"’ĕ·lō·he·ḵā","strongs":"H430","morph":"N-mpc | 2ms","gloss":"your God"},{"w":"עִמְּךָ֙","translit":"‘im·mə·ḵā","strongs":"H5973","morph":"Prep | 2ms","gloss":"is with"},{"w":"בְּכֹ֖ל","translit":"bə·ḵōl","strongs":"H3605","morph":"Prep-b | N-ms","gloss":"you wherever"},{"w":"אֲשֶׁ֥ר","translit":"’ă·šer","strongs":"H834","morph":"Pro-r","gloss":"-"},{"w":"תֵּלֵֽךְ׃פ","translit":"tê·lêḵ","strongs":"H1980","morph":"V-Qal-Imperf-2ms","gloss":"you go"}],"10":[{"w":"יְהוֹשֻׁ֔עַ","translit":"yə·hō·wō·šu·a‘","strongs":"H3091","morph":"N-proper-ms","gloss":"Then Joshua"},{"w":"אֶת־","translit":"’eṯ-","strongs":"H853","morph":"DirObjM","gloss":"-"},{"w":"וַיְצַ֣ו","translit":"way·ṣaw","strongs":"H6680","morph":"Conj-w | V-Piel-ConsecImperf-3ms","gloss":"commanded"},{"w":"שֹׁטְרֵ֥י","translit":"šō·ṭə·rê","strongs":"H7860","morph":"N-mpc","gloss":"the officers"},{"w":"הָעָ֖ם","translit":"hā·‘ām","strongs":"H5971","morph":"Art | N-ms","gloss":"of the people"},{"w":"לֵאמֹֽר׃","translit":"lê·mōr","strongs":"H559","morph":"Prep-l | V-Qal-Inf","gloss":". . ."}],"11":[{"w":"עִבְר֣וּ׀","translit":"‘iḇ·rū","strongs":"H5674","morph":"V-Qal-Imp-mp","gloss":"Go"},{"w":"בְּקֶ֣רֶב","translit":"bə·qe·reḇ","strongs":"H7130","morph":"Prep-b | N-msc","gloss":"through"},{"w":"הַֽמַּחֲנֶ֗ה","translit":"ham·ma·ḥă·neh","strongs":"H4264","morph":"Art | N-cs","gloss":"the camp"},{"w":"וְצַוּ֤וּ","translit":"wə·ṣaw·wū","strongs":"H6680","morph":"Conj-w | V-Piel-Imp-mp","gloss":"and tell"},{"w":"אֶת־","translit":"’eṯ-","strongs":"H853","morph":"DirObjM","gloss":"-"},{"w":"הָעָם֙","translit":"hā·‘ām","strongs":"H5971","morph":"Art | N-ms","gloss":"the people"},{"w":"לֵאמֹ֔ר","translit":"lê·mōr","strongs":"H559","morph":"Prep-l | V-Qal-Inf","gloss":". . ."},{"w":"הָכִ֥ינוּ","translit":"hā·ḵî·nū","strongs":"H3559","morph":"V-Hifil-Imp-mp","gloss":"Prepare"},{"w":"לָכֶ֖ם","translit":"lā·ḵem","morph":"Prep | 2mp","gloss":"your"},{"w":"צֵידָ֑ה","translit":"ṣê·ḏāh","strongs":"H6720","morph":"N-fs","gloss":"provisions"},{"w":"כִּ֞י","translit":"kî","strongs":"H3588","morph":"Conj","gloss":"for"},{"w":"בְּע֣וֹד׀","translit":"bə·‘ō·wḏ","strongs":"H5750","morph":"Prep-b | Adv","gloss":"within"},{"w":"שְׁלֹ֣שֶׁת","translit":"šə·lō·šeṯ","strongs":"H7969","morph":"Number-msc","gloss":"three"},{"w":"יָמִ֗ים","translit":"yā·mîm","strongs":"H3117","morph":"N-mp","gloss":"days"},{"w":"אַתֶּם֙","translit":"’at·tem","strongs":"H859","morph":"Pro-2mp","gloss":"you"},{"w":"עֹֽבְרִים֙","translit":"‘ō·ḇə·rîm","strongs":"H5674","morph":"V-Qal-Prtcpl-mp","gloss":"will cross"},{"w":"אֶת־","translit":"’eṯ-","strongs":"H853","morph":"DirObjM","gloss":"-"},{"w":"הַזֶּ֔ה","translit":"haz·zeh","strongs":"H2088","morph":"Art | Pro-ms","gloss":"the"},{"w":"הַיַּרְדֵּ֣ן","translit":"hay·yar·dên","strongs":"H3383","morph":"Art | N-proper-fs","gloss":"Jordan"},{"w":"לָבוֹא֙","translit":"lā·ḇō·w","strongs":"H935","morph":"Prep-l | V-Qal-Inf","gloss":"to go in"},{"w":"לָרֶ֣שֶׁת","translit":"lā·re·šeṯ","strongs":"H3423","morph":"Prep-l | V-Qal-Inf","gloss":"and take possession of"},{"w":"אֶת־","translit":"’eṯ-","strongs":"H853","morph":"DirObjM","gloss":"-"},{"w":"הָאָ֔רֶץ","translit":"hā·’ā·reṣ","strongs":"H776","morph":"Art | N-fs","gloss":"the land"},{"w":"אֲשֶׁר֙","translit":"’ă·šer","strongs":"H834","morph":"Pro-r","gloss":"that"},{"w":"יְהוָ֣ה","translit":"Yah·weh","strongs":"H3068","morph":"N-proper-ms","gloss":"the LORD"},{"w":"אֱלֹֽהֵיכֶ֔ם","translit":"’ĕ·lō·hê·ḵem","strongs":"H430","morph":"N-mpc | 2mp","gloss":"your God"},{"w":"נֹתֵ֥ן","translit":"nō·ṯên","strongs":"H5414","morph":"V-Qal-Prtcpl-ms","gloss":"is giving"},{"w":"לָכֶ֖ם","translit":"lā·ḵem","morph":"Prep | 2mp","gloss":"you"},{"w":"לְרִשְׁתָּֽהּ׃ס","translit":"lə·riš·tāh","strongs":"H3423","morph":"Prep-l | V-Qal-Inf | 3fs","gloss":"to possess"}],"12":[{"w":"וְלָרֽאוּבֵנִי֙","translit":"wə·lā·r·’ū·ḇê·nî","strongs":"H7206","morph":"Conj-w, Prep-l | N-proper-ms","gloss":"But to the Reubenites"},{"w":"וְלַגָּדִ֔י","translit":"wə·lag·gā·ḏî","strongs":"H1425","morph":"Conj-w, Prep-l, Art | N-proper-ms","gloss":"the Gadites"},{"w":"וְלַחֲצִ֖י","translit":"wə·la·ḥă·ṣî","strongs":"H2677","morph":"Conj-w, Prep-l, Art | N-msc","gloss":"and the half-tribe"},{"w":"שֵׁ֣בֶט","translit":"šê·ḇeṭ","strongs":"H7626","morph":"N-msc","gloss":". . ."},{"w":"הַֽמְנַשֶּׁ֑ה","translit":"ham·naš·šeh","strongs":"H4519","morph":"Art | N-proper-ms","gloss":"of Manasseh"},{"w":"יְהוֹשֻׁ֖עַ","translit":"yə·hō·wō·šu·a‘","strongs":"H3091","morph":"N-proper-ms","gloss":"Joshua"},{"w":"לֵאמֹֽר׃","translit":"lê·mōr","strongs":"H559","morph":"Prep-l | V-Qal-Inf","gloss":". . ."},{"w":"אָמַ֥ר","translit":"’ā·mar","strongs":"H559","morph":"V-Qal-Perf-3ms","gloss":"said"}],"13":[{"w":"זָכוֹר֙","translit":"zā·ḵō·wr","strongs":"H2142","morph":"V-Qal-InfAbs","gloss":"Remember"},{"w":"אֶת־","translit":"’eṯ-","strongs":"H853","morph":"DirObjM","gloss":"-"},{"w":"הַדָּבָ֔ר","translit":"had·dā·ḇār","strongs":"H1697","morph":"Art | N-ms","gloss":"-"},{"w":"אֲשֶׁ֨ר","translit":"’ă·šer","strongs":"H834","morph":"Pro-r","gloss":"what"},{"w":"מֹשֶׁ֥ה","translit":"mō·šeh","strongs":"H4872","morph":"N-proper-ms","gloss":"Moses"},{"w":"עֶֽבֶד־","translit":"‘e·ḇeḏ-","strongs":"H5650","morph":"N-msc","gloss":"the servant"},{"w":"יְהוָ֖ה","translit":"Yah·weh","strongs":"H3068","morph":"N-proper-ms","gloss":"of the LORD"},{"w":"צִוָּ֥ה","translit":"ṣiw·wāh","strongs":"H6680","morph":"V-Piel-Perf-3ms","gloss":"commanded"},{"w":"אֶתְכֶ֛ם","translit":"’eṯ·ḵem","strongs":"H853","morph":"DirObjM | 2mp","gloss":"you"},{"w":"לֵאמֹ֑ר","translit":"lê·mōr","strongs":"H559","morph":"Prep-l | V-Qal-Inf","gloss":"when he said"},{"w":"יְהוָ֤ה","translit":"Yah·weh","strongs":"H3068","morph":"N-proper-ms","gloss":"The LORD"},{"w":"אֱלֹהֵיכֶם֙","translit":"’ĕ·lō·hê·ḵem","strongs":"H430","morph":"N-mpc | 2mp","gloss":"your God"},{"w":"מֵנִ֣יחַ","translit":"mê·nî·aḥ","strongs":"H5117","morph":"V-Hifil-Prtcpl-ms","gloss":"will give you rest"},{"w":"לָכֶ֔ם","translit":"lā·ḵem","morph":"Prep | 2mp"},{"w":"וְנָתַ֥ן","translit":"wə·nā·ṯan","strongs":"H5414","morph":"Conj-w | V-Qal-ConjPerf-3ms","gloss":"and He will give"},{"w":"לָכֶ֖ם","translit":"lā·ḵem","morph":"Prep | 2mp","gloss":"you"},{"w":"אֶת־","translit":"’eṯ-","strongs":"H853","morph":"DirObjM"},{"w":"הַזֹּֽאת׃","translit":"haz·zōṯ","strongs":"H2063","morph":"Art | Pro-fs","gloss":"this"},{"w":"הָאָ֥רֶץ","translit":"hā·’ā·reṣ","strongs":"H776","morph":"Art | N-fs","gloss":"land"}],"14":[{"w":"נְשֵׁיכֶ֣ם","translit":"nə·šê·ḵem","strongs":"H802","morph":"N-fpc | 2mp","gloss":"Your wives"},{"w":"טַפְּכֶם֮","translit":"ṭap·pə·ḵem","strongs":"H2945","morph":"N-msc | 2mp","gloss":"your young children"},{"w":"וּמִקְנֵיכֶם֒","translit":"ū·miq·nê·ḵem","strongs":"H4735","morph":"Conj-w | N-mpc | 2mp","gloss":"and your livestock"},{"w":"יֵשְׁב֕וּ","translit":"yê·šə·ḇū","strongs":"H3427","morph":"V-Qal-Imperf-3mp","gloss":"may remain"},{"w":"בָּאָ֕רֶץ","translit":"bā·’ā·reṣ","strongs":"H776","morph":"Prep-b, Art | N-fs","gloss":"in the land"},{"w":"אֲשֶׁ֨ר","translit":"’ă·šer","strongs":"H834","morph":"Pro-r","gloss":"that"},{"w":"מֹשֶׁ֖ה","translit":"mō·šeh","strongs":"H4872","morph":"N-proper-ms","gloss":"Moses"},{"w":"נָתַ֥ן","translit":"nā·ṯan","strongs":"H5414","morph":"V-Qal-Perf-3ms","gloss":"gave"},{"w":"לָכֶ֛ם","translit":"lā·ḵem","morph":"Prep | 2mp","gloss":"you"},{"w":"בְּעֵ֣בֶר","translit":"bə·‘ê·ḇer","strongs":"H5676","morph":"Prep-b | N-msc","gloss":"on this side"},{"w":"הַיַּרְדֵּ֑ן","translit":"hay·yar·dên","strongs":"H3383","morph":"Art | N-proper-fs","gloss":"of the Jordan"},{"w":"וְאַתֶּם֩","translit":"wə·’at·tem","strongs":"H859","morph":"Conj-w | Pro-2mp","gloss":". . ."},{"w":"כֹּ֚ל","translit":"kōl","strongs":"H3605","morph":"N-msc","gloss":"But all"},{"w":"גִּבּוֹרֵ֣י","translit":"gib·bō·w·rê","strongs":"H1368","morph":"Adj-mpc","gloss":"your mighty men"},{"w":"הַחַ֔יִל","translit":"ha·ḥa·yil","strongs":"H2428","morph":"Art | N-ms","gloss":"of valor"},{"w":"חֲמֻשִׁ֜ים","translit":"ḥă·mu·šîm","strongs":"H2571","morph":"V-Qal-QalPassPrtcpl-mp","gloss":"must be armed for battle"},{"w":"תַּעַבְר֨וּ","translit":"ta·‘aḇ·rū","strongs":"H5674","morph":"V-Qal-Imperf-2mp","gloss":"to cross over"},{"w":"לִפְנֵ֣י","translit":"lip̄·nê","strongs":"H6440","morph":"Prep-l | N-cpc","gloss":"ahead of"},{"w":"אֲחֵיכֶ֗ם","translit":"’ă·ḥê·ḵem","strongs":"H251","morph":"N-mpc | 2mp","gloss":"your brothers"},{"w":"וַעֲזַרְתֶּ֖ם","translit":"wa·‘ă·zar·tem","strongs":"H5826","morph":"Conj-w | V-Qal-ConjPerf-2mp","gloss":"and help them"},{"w":"אוֹתָֽם׃","translit":"’ō·w·ṯām","strongs":"H853","morph":"DirObjM | 3mp","gloss":"-"}],"15":[{"w":"עַ֠ד","translit":"‘aḏ","strongs":"H5704","morph":"Prep","gloss":"until"},{"w":"אֲשֶׁר־","translit":"’ă·šer-","strongs":"H834","morph":"Pro-r","gloss":"-"},{"w":"יְהוָ֥ה׀","translit":"Yah·weh","strongs":"H3068","morph":"N-proper-ms","gloss":"the LORD"},{"w":"יָנִ֨יחַ","translit":"yā·nî·aḥ","strongs":"H5117","morph":"V-Hifil-Imperf-3ms","gloss":"gives [them] rest"},{"w":"לַֽאֲחֵיכֶם֮","translit":"la·’ă·ḥê·ḵem","strongs":"H251","morph":"Prep-l | N-mpc | 2mp","gloss":". . ."},{"w":"כָּכֶם֒","translit":"kā·ḵem","morph":"Prep | 2mp","gloss":"as He has done for you"},{"w":"הֵ֔מָּה","translit":"hêm·māh","strongs":"H1992","morph":"Pro-3mp","gloss":"and [your brothers]"},{"w":"אֶת־","translit":"’eṯ-","strongs":"H853","morph":"DirObjM","gloss":"-"},{"w":"גַם־","translit":"ḡam-","strongs":"H1571","morph":"Conj","gloss":"also"},{"w":"וְיָרְשׁ֣וּ","translit":"wə·yā·rə·šū","strongs":"H3423","morph":"Conj-w | V-Qal-ConjPerf-3cp","gloss":"possess"},{"w":"הָאָ֕רֶץ","translit":"hā·’ā·reṣ","strongs":"H776","morph":"Art | N-fs","gloss":"the land"},{"w":"אֲשֶׁר־","translit":"’ă·šer-","strongs":"H834","morph":"Pro-r","gloss":"that"},{"w":"יְהוָ֥ה","translit":"Yah·weh","strongs":"H3068","morph":"N-proper-ms","gloss":"the LORD"},{"w":"אֱלֹֽהֵיכֶ֖ם","translit":"’ĕ·lō·hê·ḵem","strongs":"H430","morph":"N-mpc | 2mp","gloss":"your God"},{"w":"נֹתֵ֣ן","translit":"nō·ṯên","strongs":"H5414","morph":"V-Qal-Prtcpl-ms","gloss":"is giving"},{"w":"לָהֶ֑ם","translit":"lā·hem","morph":"Prep | 3mp","gloss":"them"},{"w":"וְשַׁבְתֶּ֞ם","translit":"wə·šaḇ·tem","strongs":"H7725","morph":"Conj-w | V-Qal-ConjPerf-2mp","gloss":"Then you may return"},{"w":"לְאֶ֤רֶץ","translit":"lə·’e·reṣ","strongs":"H776","morph":"Prep-l | N-fsc","gloss":"to the land"},{"w":"יְרֻשַּׁתְכֶם֙","translit":"yə·ruš·šaṯ·ḵem","strongs":"H3425","morph":"N-fsc | 2mp","gloss":"of your inheritance"},{"w":"וִֽירִשְׁתֶּ֣ם","translit":"wî·riš·tem","strongs":"H3423","morph":"Conj-w | V-Qal-ConjPerf-2mp","gloss":"and take possession of"},{"w":"אוֹתָ֔הּ","translit":"’ō·w·ṯāh","strongs":"H853","morph":"DirObjM | 3fs","gloss":"-"},{"w":"אֲשֶׁ֣ר׀","translit":"’ă·šer","strongs":"H834","morph":"Pro-r","gloss":"that which"},{"w":"מֹשֶׁה֙","translit":"mō·šeh","strongs":"H4872","morph":"N-proper-ms","gloss":"Moses"},{"w":"עֶ֣בֶד","translit":"‘e·ḇeḏ","strongs":"H5650","morph":"N-msc","gloss":"the servant"},{"w":"יְהוָ֔ה","translit":"Yah·weh","strongs":"H3068","morph":"N-proper-ms","gloss":"of the LORD"},{"w":"נָתַ֣ן","translit":"nā·ṯan","strongs":"H5414","morph":"V-Qal-Perf-3ms","gloss":"gave"},{"w":"לָכֶ֗ם","translit":"lā·ḵem","morph":"Prep | 2mp","gloss":"you"},{"w":"מִזְרַ֥ח","translit":"miz·raḥ","strongs":"H4217","morph":"N-msc","gloss":"on the east"},{"w":"הַשָּֽׁמֶשׁ׃","translit":"haš·šā·meš","strongs":"H8121","morph":"Art | N-cs","gloss":". . ."},{"w":"בְּעֵ֥בֶר","translit":"bə·‘ê·ḇer","strongs":"H5676","morph":"Prep-b | N-msc","gloss":"side"},{"w":"הַיַּרְדֵּ֖ן","translit":"hay·yar·dên","strongs":"H3383","morph":"Art | N-proper-fs","gloss":"of the Jordan"}],"16":[{"w":"וַֽיַּעֲנ֔וּ","translit":"way·ya·‘ă·nū","strongs":"H6030","morph":"Conj-w | V-Qal-ConsecImperf-3mp","gloss":"So they answered"},{"w":"אֶת־","translit":"’eṯ-","strongs":"H853","morph":"DirObjM","gloss":"-"},{"w":"יְהוֹשֻׁ֖עַ","translit":"yə·hō·wō·šu·a‘","strongs":"H3091","morph":"N-proper-ms","gloss":"Joshua"},{"w":"לֵאמֹ֑ר","translit":"lê·mōr","strongs":"H559","morph":"Prep-l | V-Qal-Inf","gloss":". . ."},{"w":"אֲשֶׁר־","translit":"’ă·šer-","strongs":"H834","morph":"Pro-r"},{"w":"כֹּ֤ל","translit":"kōl","strongs":"H3605","morph":"N-ms","gloss":"Everything"},{"w":"צִוִּיתָ֙נוּ֙","translit":"ṣiw·wî·ṯā·nū","strongs":"H6680","morph":"V-Piel-Perf-2ms | 1cp","gloss":"you have commanded us"},{"w":"נַֽעֲשֶׂ֔ה","translit":"na·‘ă·śeh","strongs":"H6213","morph":"V-Qal-Imperf-1cp","gloss":"we will do"},{"w":"וְאֶֽל־","translit":"wə·’el-","strongs":"H413","morph":"Conj-w | Prep","gloss":"and everywhere"},{"w":"כָּל־","translit":"kāl-","strongs":"H3605","morph":"N-msc","gloss":". . ."},{"w":"אֲשֶׁ֥ר","translit":"’ă·šer","strongs":"H834","morph":"Pro-r","gloss":"-"},{"w":"תִּשְׁלָחֵ֖נוּ","translit":"tiš·lā·ḥê·nū","strongs":"H7971","morph":"V-Qal-Imperf-2ms | 1cp","gloss":"you send us"},{"w":"נֵלֵֽךְ׃","translit":"nê·lêḵ","strongs":"H1980","morph":"V-Qal-Imperf-1cp","gloss":"we will go"}],"17":[{"w":"אֲשֶׁר־","translit":"’ă·šer-","strongs":"H834","morph":"Pro-r","gloss":"Just as"},{"w":"נִשְׁמַ֣ע","translit":"niš·ma‘","strongs":"H8085","morph":"V-Qal-Imperf-1cp","gloss":"we obeyed"},{"w":"אֵלֶ֑יךָ","translit":"’ê·le·ḵā","strongs":"H413","morph":"Prep | 2ms","gloss":". . ."},{"w":"רַ֠ק","translit":"raq","strongs":"H7535","morph":"Adv","gloss":". . ."},{"w":"מֹשֶׁ֔ה","translit":"mō·šeh","strongs":"H4872","morph":"N-proper-ms","gloss":"Moses"},{"w":"כֵּ֖ן","translit":"kên","strongs":"H3651","morph":"Adv","gloss":". . ."},{"w":"כְּכֹ֤ל","translit":"kə·ḵōl","strongs":"H3605","morph":"Prep-k | N-ms","gloss":"in all things"},{"w":"שָׁמַ֙עְנוּ֙","translit":"šā·ma‘·nū","strongs":"H8085","morph":"V-Qal-Perf-1cp","gloss":"so we will obey you"},{"w":"אֶל־","translit":"’el-","strongs":"H413","morph":"Prep","gloss":". . ."},{"w":"יְהוָ֤ה","translit":"Yah·weh","strongs":"H3068","morph":"N-proper-ms","gloss":"And may the LORD"},{"w":"אֱלֹהֶ֙יךָ֙","translit":"’ĕ·lō·he·ḵā","strongs":"H430","morph":"N-mpc | 2ms","gloss":"your God"},{"w":"יִֽהְיֶ֞ה","translit":"yih·yeh","strongs":"H1961","morph":"V-Qal-Imperf-3ms","gloss":"be"},{"w":"עִמָּ֔ךְ","translit":"‘im·māḵ","strongs":"H5973","morph":"Prep | 2fs","gloss":"with you"},{"w":"כַּאֲשֶׁ֥ר","translit":"ka·’ă·šer","strongs":"H834","morph":"Prep-k | Pro-r","gloss":"as"},{"w":"הָיָ֖ה","translit":"hā·yāh","strongs":"H1961","morph":"V-Qal-Perf-3ms","gloss":"He was"},{"w":"עִם־","translit":"‘im-","strongs":"H5973","morph":"Prep","gloss":"with"},{"w":"מֹשֶֽׁה׃","translit":"mō·šeh","strongs":"H4872","morph":"N-proper-ms","gloss":"Moses"}],"18":[{"w":"כָּל־","translit":"kāl-","strongs":"H3605","morph":"N-msc","gloss":"Anyone"},{"w":"אִ֞ישׁ","translit":"’îš","strongs":"H376","morph":"N-ms","gloss":". . ."},{"w":"אֲשֶׁר־","translit":"’ă·šer-","strongs":"H834","morph":"Pro-r","gloss":"who"},{"w":"יַמְרֶ֣ה","translit":"yam·reh","strongs":"H4784","morph":"V-Hifil-Imperf-3ms","gloss":"rebels"},{"w":"אֶת־","translit":"’eṯ-","strongs":"H853","morph":"DirObjM","gloss":"-"},{"w":"פִּ֗יךָ","translit":"pî·ḵā","strongs":"H6310","morph":"N-msc | 2ms","gloss":"against your order"},{"w":"וְלֹֽא־","translit":"wə·lō-","strongs":"H3808","morph":"Conj-w | Adv-NegPrt","gloss":"and does not"},{"w":"יִשְׁמַ֧ע","translit":"yiš·ma‘","strongs":"H8085","morph":"V-Qal-Imperf-3ms","gloss":"obey"},{"w":"אֶת־","translit":"’eṯ-","strongs":"H853","morph":"DirObjM","gloss":"-"},{"w":"דְּבָרֶ֛יךָ","translit":"də·ḇā·re·ḵā","strongs":"H1697","morph":"N-mpc | 2ms","gloss":"your words"},{"w":"לְכֹ֥ל","translit":"lə·ḵōl","strongs":"H3605","morph":"Prep-l | N-ms","gloss":"all"},{"w":"אֲשֶׁר־","translit":"’ă·šer-","strongs":"H834","morph":"Pro-r","gloss":"that"},{"w":"תְּצַוֶּ֖נּוּ","translit":"tə·ṣaw·wen·nū","strongs":"H6680","morph":"V-Piel-Imperf-2ms | 3ms","gloss":"you command him"},{"w":"יוּמָ֑ת","translit":"yū·māṯ","strongs":"H4191","morph":"V-Hofal-Imperf-3ms","gloss":"will be put to death"},{"w":"רַ֖ק","translit":"raq","strongs":"H7535","morph":"Adv","gloss":"Above all"},{"w":"חֲזַ֥ק","translit":"ḥă·zaq","strongs":"H2388","morph":"V-Qal-Imp-ms","gloss":"be strong"},{"w":"וֶאֱמָֽץ׃פ","translit":"we·’ĕ·māṣ","strongs":"H553","morph":"Conj-w | V-Qal-Imp-ms","gloss":"and courageous"}]}}